Lab8_microphone/rtl/i2s/i2s.v
module i2s(
    input clk,
    input rst_n,
    output WS,
    output BCLK,
    input DIN,
    output reg done,
    output reg [size -1:0] data,
    input en,
    input ack_data,
    input ack_done
);

reg BCLK_d, WS_d;
localparam size = 32;
reg [$clog2(size) -1:0] bit_count;
reg [size -1 : 0] shift_reg;


// WS
always @(posedge clk, negedge rst_n) begin
    if(!rst_n) begin
        WS_d <= 0;
    end
    else if(en) begin
        if(bit_count >= size) begin
            WS_d <= 1;
        end
        else WS_d <= 0;
    end
end

// BCLK

always @(posedge clk, negedge rst_n) begin
    if (!rst_n) begin
        BCLK_d <= 0;
    end
    else if(en) begin
        BCLK_d <= !BCLK_d;
    end
end

// bit_counter 

always @(posedge clk, negedge rst_n) begin
     if (!rst_n) begin
        bit_count <= 0;
    end
    else if(en) begin
        if(BCLK_d) begin 
            bit_count <= bit_count + 1;
        end
    end
end

// shift register

always @(posedge clk, negedge rst_n) begin
     if (!rst_n) begin
        shift_reg <= 32'd0;
    end
    else if(en && BCLK_d) begin
        if(bit_count < size -1) begin 
            shift_reg <= {shift_reg[size -2 : 0],DIN};
        end
        else shift_reg <= 32'd0;
    end
end


// done
always @(posedge clk, negedge rst_n) begin
    if (!rst_n) begin
        done <= 0;
    end
    else if(en) begin
        if(bit_count == size -1) begin
            done <= 1;
        end
        else if(ack_done) begin
            done <= 0;
        end
    end
end

// data
always @(posedge clk, negedge rst_n) begin
    if (!rst_n) begin
        data <= 0;
    end
    else if(en) begin
        if(bit_count == size -1) begin
            data <= shift_reg;
        end
        else if(ack_data) begin
            data <= shift_reg;
        end
    end
end

assign WS = WS_d;
assign BCLK = BCLK_d;


endmodule

Lab8_microphone/rtl/i2s/i2s_tb.v
module i2s_tb;
    reg clk = 0;
    reg rst_n = 0;
    wire WS;
    wire BCLK;
    reg DIN;
    wire done;
    wire [31:0] data;
    reg en;
    reg [5:0] counter;

    i2s duv (
        .clk(clk),
        .rst_n(rst_n),
        .WS(WS),
        .BCLK(BCLK),
        .DIN(DIN),
        .done(done),
        .data(data),
        .en(en)
    );

    always #10 clk = !clk;

    initial begin
        #777;
        @(posedge clk);
        #1; 
        rst_n = 1;
    end

    initial begin
        $dumpfile("i2s_tb.vcd");
        $dumpvars;
    end

    initial begin
        en = 0;
        DIN = 0;
        wait(rst_n == 1'b1);
        @(posedge clk);
        en = 1;
        #10000;
        $finish;
    end

    always@(posedge clk or WS) begin
        if(WS) 
            DIN = 1;
    end




endmodule

Lab8_microphone/rtl/i2s/i2s_tb.vcd
$date
	Wed Oct 30 12:31:04 2024
$end
$version
	Icarus Verilog
$end
$timescale
	1s
$end
$scope module i2s_tb $end
$var wire 1 ! done $end
$var wire 32 " data [31:0] $end
$var wire 1 # WS $end
$var wire 1 $ BCLK $end
$var reg 1 % DIN $end
$var reg 1 & clk $end
$var reg 1 ' en $end
$var reg 1 ( rst_n $end
$scope module duv $end
$var wire 1 $ BCLK $end
$var wire 1 % DIN $end
$var wire 1 # WS $end
$var wire 1 ) ack_data $end
$var wire 1 * ack_done $end
$var wire 1 & clk $end
$var wire 1 ' en $end
$var wire 1 ( rst_n $end
$var reg 1 + BCLK_d $end
$var reg 1 , WS_d $end
$var reg 6 - bit_count [5:0] $end
$var reg 64 . data [63:0] $end
$var reg 1 ! done $end
$var reg 64 / shift_reg [63:0] $end
$upscope $end
$upscope $end
$enddefinitions $end
#0
$dumpvars
b0 /
b0 .
b0 -
0,
0+
z*
z)
0(
0'
0&
0%
0$
0#
b0 "
0!
$end
#10
1&
#20
0&
#30
1&
#40
0&
#50
1&
#60
0&
#70
1&
#80
0&
#90
1&
#100
0&
#110
1&
#120
0&
#130
1&
#140
0&
#150
1&
#160
0&
#170
1&
#180
0&
#190
1&
#200
0&
#210
1&
#220
0&
#230
1&
#240
0&
#250
1&
#260
0&
#270
1&
#280
0&
#290
1&
#300
0&
#310
1&
#320
0&
#330
1&
#340
0&
#350
1&
#360
0&
#370
1&
#380
0&
#390
1&
#400
0&
#410
1&
#420
0&
#430
1&
#440
0&
#450
1&
#460
0&
#470
1&
#480
0&
#490
1&
#500
0&
#510
1&
#520
0&
#530
1&
#540
0&
#550
1&
#560
0&
#570
1&
#580
0&
#590
1&
#600
0&
#610
1&
#620
0&
#630
1&
#640
0&
#650
1&
#660
0&
#670
1&
#680
0&
#690
1&
#700
0&
#710
1&
#720
0&
#730
1&
#740
0&
#750
1&
#760
0&
#770
1&
#780
0&
#790
1&
#791
1(
#800
0&
#810
1$
1+
1'
1&
#820
0&
#830
0$
0+
b1 -
1&
#840
0&
#850
1$
1+
1&
#860
0&
#870
0$
0+
b10 -
1&
#880
0&
#890
1$
1+
1&
#900
0&
#910
0$
0+
b11 -
1&
#920
0&
#930
1$
1+
1&
#940
0&
#950
0$
0+
b100 -
1&
#960
0&
#970
1$
1+
1&
#980
0&
#990
0$
0+
b101 -
1&
#1000
0&
#1010
1$
1+
1&
#1020
0&
#1030
0$
0+
b110 -
1&
#1040
0&
#1050
1$
1+
1&
#1060
0&
#1070
0$
0+
b111 -
1&
#1080
0&
#1090
1$
1+
1&
#1100
0&
#1110
0$
0+
b1000 -
1&
#1120
0&
#1130
1$
1+
1&
#1140
0&
#1150
0$
0+
b1001 -
1&
#1160
0&
#1170
1$
1+
1&
#1180
0&
#1190
0$
0+
b1010 -
1&
#1200
0&
#1210
1$
1+
1&
#1220
0&
#1230
0$
0+
b1011 -
1&
#1240
0&
#1250
1$
1+
1&
#1260
0&
#1270
0$
0+
b1100 -
1&
#1280
0&
#1290
1$
1+
1&
#1300
0&
#1310
0$
0+
b1101 -
1&
#1320
0&
#1330
1$
1+
1&
#1340
0&
#1350
0$
0+
b1110 -
1&
#1360
0&
#1370
1$
1+
1&
#1380
0&
#1390
0$
0+
b1111 -
1&
#1400
0&
#1410
1$
1+
1&
#1420
0&
#1430
0$
0+
b10000 -
1&
#1440
0&
#1450
1$
1+
1&
#1460
0&
#1470
0$
0+
b10001 -
1&
#1480
0&
#1490
1$
1+
1&
#1500
0&
#1510
0$
0+
b10010 -
1&
#1520
0&
#1530
1$
1+
1&
#1540
0&
#1550
0$
0+
b10011 -
1&
#1560
0&
#1570
1$
1+
1&
#1580
0&
#1590
0$
0+
b10100 -
1&
#1600
0&
#1610
1$
1+
1&
#1620
0&
#1630
0$
0+
b10101 -
1&
#1640
0&
#1650
1$
1+
1&
#1660
0&
#1670
0$
0+
b10110 -
1&
#1680
0&
#1690
1$
1+
1&
#1700
0&
#1710
0$
0+
b10111 -
1&
#1720
0&
#1730
1$
1+
1&
#1740
0&
#1750
0$
0+
b11000 -
1&
#1760
0&
#1770
1$
1+
1&
#1780
0&
#1790
0$
0+
b11001 -
1&
#1800
0&
#1810
1$
1+
1&
#1820
0&
#1830
0$
0+
b11010 -
1&
#1840
0&
#1850
1$
1+
1&
#1860
0&
#1870
0$
0+
b11011 -
1&
#1880
0&
#1890
1$
1+
1&
#1900
0&
#1910
0$
0+
b11100 -
1&
#1920
0&
#1930
1$
1+
1&
#1940
0&
#1950
0$
0+
b11101 -
1&
#1960
0&
#1970
1$
1+
1&
#1980
0&
#1990
0$
0+
b11110 -
1&
#2000
0&
#2010
1$
1+
1&
#2020
0&
#2030
0$
0+
b11111 -
1&
#2040
0&
#2050
1$
1+
1&
#2060
0&
#2070
0$
0+
b100000 -
1&
#2080
0&
#2090
1%
1$
1+
1#
1,
1&
#2100
0&
#2110
0$
0+
b100001 -
b1 /
1&
#2120
0&
#2130
1$
1+
1&
#2140
0&
#2150
0$
0+
b100010 -
b11 /
1&
#2160
0&
#2170
1$
1+
1&
#2180
0&
#2190
0$
0+
b100011 -
b111 /
1&
#2200
0&
#2210
1$
1+
1&
#2220
0&
#2230
0$
0+
b100100 -
b1111 /
1&
#2240
0&
#2250
1$
1+
1&
#2260
0&
#2270
0$
0+
b100101 -
b11111 /
1&
#2280
0&
#2290
1$
1+
1&
#2300
0&
#2310
0$
0+
b100110 -
b111111 /
1&
#2320
0&
#2330
1$
1+
1&
#2340
0&
#2350
0$
0+
b100111 -
b1111111 /
1&
#2360
0&
#2370
1$
1+
1&
#2380
0&
#2390
0$
0+
b101000 -
b11111111 /
1&
#2400
0&
#2410
1$
1+
1&
#2420
0&
#2430
0$
0+
b101001 -
b111111111 /
1&
#2440
0&
#2450
1$
1+
1&
#2460
0&
#2470
0$
0+
b101010 -
b1111111111 /
1&
#2480
0&
#2490
1$
1+
1&
#2500
0&
#2510
0$
0+
b101011 -
b11111111111 /
1&
#2520
0&
#2530
1$
1+
1&
#2540
0&
#2550
0$
0+
b101100 -
b111111111111 /
1&
#2560
0&
#2570
1$
1+
1&
#2580
0&
#2590
0$
0+
b101101 -
b1111111111111 /
1&
#2600
0&
#2610
1$
1+
1&
#2620
0&
#2630
0$
0+
b101110 -
b11111111111111 /
1&
#2640
0&
#2650
1$
1+
1&
#2660
0&
#2670
0$
0+
b101111 -
b111111111111111 /
1&
#2680
0&
#2690
1$
1+
1&
#2700
0&
#2710
0$
0+
b110000 -
b1111111111111111 /
1&
#2720
0&
#2730
1$
1+
1&
#2740
0&
#2750
0$
0+
b110001 -
b11111111111111111 /
1&
#2760
0&
#2770
1$
1+
1&
#2780
0&
#2790
0$
0+
b110010 -
b111111111111111111 /
1&
#2800
0&
#2810
1$
1+
1&
#2820
0&
#2830
0$
0+
b110011 -
b1111111111111111111 /
1&
#2840
0&
#2850
1$
1+
1&
#2860
0&
#2870
0$
0+
b110100 -
b11111111111111111111 /
1&
#2880
0&
#2890
1$
1+
1&
#2900
0&
#2910
0$
0+
b110101 -
b111111111111111111111 /
1&
#2920
0&
#2930
1$
1+
1&
#2940
0&
#2950
0$
0+
b110110 -
b1111111111111111111111 /
1&
#2960
0&
#2970
1$
1+
1&
#2980
0&
#2990
0$
0+
b110111 -
b11111111111111111111111 /
1&
#3000
0&
#3010
1$
1+
1&
#3020
0&
#3030
0$
0+
b111000 -
b111111111111111111111111 /
1&
#3040
0&
#3050
1$
1+
1&
#3060
0&
#3070
0$
0+
b111001 -
b1111111111111111111111111 /
1&
#3080
0&
#3090
1$
1+
1&
#3100
0&
#3110
0$
0+
b111010 -
b11111111111111111111111111 /
1&
#3120
0&
#3130
1$
1+
1&
#3140
0&
#3150
0$
0+
b111011 -
b111111111111111111111111111 /
1&
#3160
0&
#3170
1$
1+
1&
#3180
0&
#3190
0$
0+
b111100 -
b1111111111111111111111111111 /
1&
#3200
0&
#3210
1$
1+
1&
#3220
0&
#3230
0$
0+
b111101 -
b11111111111111111111111111111 /
1&
#3240
0&
#3250
1$
1+
1&
#3260
0&
#3270
0$
0+
b111110 -
b111111111111111111111111111111 /
1&
#3280
0&
#3290
1$
1+
1&
#3300
0&
#3310
0$
0+
b111111 -
b1111111111111111111111111111111 /
1&
#3320
0&
#3330
b1111111111111111111111111111111 "
b1111111111111111111111111111111 .
1!
1$
1+
1&
#3340
0&
#3350
0$
0+
b0 -
b0 /
1&
#3360
0&
#3370
1$
1+
0#
0,
1&
#3380
0&
#3390
0$
0+
b1 -
b1 /
1&
#3400
0&
#3410
1$
1+
1&
#3420
0&
#3430
0$
0+
b10 -
b11 /
1&
#3440
0&
#3450
1$
1+
1&
#3460
0&
#3470
0$
0+
b11 -
b111 /
1&
#3480
0&
#3490
1$
1+
1&
#3500
0&
#3510
0$
0+
b100 -
b1111 /
1&
#3520
0&
#3530
1$
1+
1&
#3540
0&
#3550
0$
0+
b101 -
b11111 /
1&
#3560
0&
#3570
1$
1+
1&
#3580
0&
#3590
0$
0+
b110 -
b111111 /
1&
#3600
0&
#3610
1$
1+
1&
#3620
0&
#3630
0$
0+
b111 -
b1111111 /
1&
#3640
0&
#3650
1$
1+
1&
#3660
0&
#3670
0$
0+
b1000 -
b11111111 /
1&
#3680
0&
#3690
1$
1+
1&
#3700
0&
#3710
0$
0+
b1001 -
b111111111 /
1&
#3720
0&
#3730
1$
1+
1&
#3740
0&
#3750
0$
0+
b1010 -
b1111111111 /
1&
#3760
0&
#3770
1$
1+
1&
#3780
0&
#3790
0$
0+
b1011 -
b11111111111 /
1&
#3800
0&
#3810
1$
1+
1&
#3820
0&
#3830
0$
0+
b1100 -
b111111111111 /
1&
#3840
0&
#3850
1$
1+
1&
#3860
0&
#3870
0$
0+
b1101 -
b1111111111111 /
1&
#3880
0&
#3890
1$
1+
1&
#3900
0&
#3910
0$
0+
b1110 -
b11111111111111 /
1&
#3920
0&
#3930
1$
1+
1&
#3940
0&
#3950
0$
0+
b1111 -
b111111111111111 /
1&
#3960
0&
#3970
1$
1+
1&
#3980
0&
#3990
0$
0+
b10000 -
b1111111111111111 /
1&
#4000
0&
#4010
1$
1+
1&
#4020
0&
#4030
0$
0+
b10001 -
b11111111111111111 /
1&
#4040
0&
#4050
1$
1+
1&
#4060
0&
#4070
0$
0+
b10010 -
b111111111111111111 /
1&
#4080
0&
#4090
1$
1+
1&
#4100
0&
#4110
0$
0+
b10011 -
b1111111111111111111 /
1&
#4120
0&
#4130
1$
1+
1&
#4140
0&
#4150
0$
0+
b10100 -
b11111111111111111111 /
1&
#4160
0&
#4170
1$
1+
1&
#4180
0&
#4190
0$
0+
b10101 -
b111111111111111111111 /
1&
#4200
0&
#4210
1$
1+
1&
#4220
0&
#4230
0$
0+
b10110 -
b1111111111111111111111 /
1&
#4240
0&
#4250
1$
1+
1&
#4260
0&
#4270
0$
0+
b10111 -
b11111111111111111111111 /
1&
#4280
0&
#4290
1$
1+
1&
#4300
0&
#4310
0$
0+
b11000 -
b111111111111111111111111 /
1&
#4320
0&
#4330
1$
1+
1&
#4340
0&
#4350
0$
0+
b11001 -
b1111111111111111111111111 /
1&
#4360
0&
#4370
1$
1+
1&
#4380
0&
#4390
0$
0+
b11010 -
b11111111111111111111111111 /
1&
#4400
0&
#4410
1$
1+
1&
#4420
0&
#4430
0$
0+
b11011 -
b111111111111111111111111111 /
1&
#4440
0&
#4450
1$
1+
1&
#4460
0&
#4470
0$
0+
b11100 -
b1111111111111111111111111111 /
1&
#4480
0&
#4490
1$
1+
1&
#4500
0&
#4510
0$
0+
b11101 -
b11111111111111111111111111111 /
1&
#4520
0&
#4530
1$
1+
1&
#4540
0&
#4550
0$
0+
b11110 -
b111111111111111111111111111111 /
1&
#4560
0&
#4570
1$
1+
1&
#4580
0&
#4590
0$
0+
b11111 -
b1111111111111111111111111111111 /
1&
#4600
0&
#4610
1$
1+
1&
#4620
0&
#4630
0$
0+
b100000 -
b11111111111111111111111111111111 /
1&
#4640
0&
#4650
1$
1+
1#
1,
1&
#4660
0&
#4670
0$
0+
b100001 -
b111111111111111111111111111111111 /
1&
#4680
0&
#4690
1$
1+
1&
#4700
0&
#4710
0$
0+
b100010 -
b1111111111111111111111111111111111 /
1&
#4720
0&
#4730
1$
1+
1&
#4740
0&
#4750
0$
0+
b100011 -
b11111111111111111111111111111111111 /
1&
#4760
0&
#4770
1$
1+
1&
#4780
0&
#4790
0$
0+
b100100 -
b111111111111111111111111111111111111 /
1&
#4800
0&
#4810
1$
1+
1&
#4820
0&
#4830
0$
0+
b100101 -
b1111111111111111111111111111111111111 /
1&
#4840
0&
#4850
1$
1+
1&
#4860
0&
#4870
0$
0+
b100110 -
b11111111111111111111111111111111111111 /
1&
#4880
0&
#4890
1$
1+
1&
#4900
0&
#4910
0$
0+
b100111 -
b111111111111111111111111111111111111111 /
1&
#4920
0&
#4930
1$
1+
1&
#4940
0&
#4950
0$
0+
b101000 -
b1111111111111111111111111111111111111111 /
1&
#4960
0&
#4970
1$
1+
1&
#4980
0&
#4990
0$
0+
b101001 -
b11111111111111111111111111111111111111111 /
1&
#5000
0&
#5010
1$
1+
1&
#5020
0&
#5030
0$
0+
b101010 -
b111111111111111111111111111111111111111111 /
1&
#5040
0&
#5050
1$
1+
1&
#5060
0&
#5070
0$
0+
b101011 -
b1111111111111111111111111111111111111111111 /
1&
#5080
0&
#5090
1$
1+
1&
#5100
0&
#5110
0$
0+
b101100 -
b11111111111111111111111111111111111111111111 /
1&
#5120
0&
#5130
1$
1+
1&
#5140
0&
#5150
0$
0+
b101101 -
b111111111111111111111111111111111111111111111 /
1&
#5160
0&
#5170
1$
1+
1&
#5180
0&
#5190
0$
0+
b101110 -
b1111111111111111111111111111111111111111111111 /
1&
#5200
0&
#5210
1$
1+
1&
#5220
0&
#5230
0$
0+
b101111 -
b11111111111111111111111111111111111111111111111 /
1&
#5240
0&
#5250
1$
1+
1&
#5260
0&
#5270
0$
0+
b110000 -
b111111111111111111111111111111111111111111111111 /
1&
#5280
0&
#5290
1$
1+
1&
#5300
0&
#5310
0$
0+
b110001 -
b1111111111111111111111111111111111111111111111111 /
1&
#5320
0&
#5330
1$
1+
1&
#5340
0&
#5350
0$
0+
b110010 -
b11111111111111111111111111111111111111111111111111 /
1&
#5360
0&
#5370
1$
1+
1&
#5380
0&
#5390
0$
0+
b110011 -
b111111111111111111111111111111111111111111111111111 /
1&
#5400
0&
#5410
1$
1+
1&
#5420
0&
#5430
0$
0+
b110100 -
b1111111111111111111111111111111111111111111111111111 /
1&
#5440
0&
#5450
1$
1+
1&
#5460
0&
#5470
0$
0+
b110101 -
b11111111111111111111111111111111111111111111111111111 /
1&
#5480
0&
#5490
1$
1+
1&
#5500
0&
#5510
0$
0+
b110110 -
b111111111111111111111111111111111111111111111111111111 /
1&
#5520
0&
#5530
1$
1+
1&
#5540
0&
#5550
0$
0+
b110111 -
b1111111111111111111111111111111111111111111111111111111 /
1&
#5560
0&
#5570
1$
1+
1&
#5580
0&
#5590
0$
0+
b111000 -
b11111111111111111111111111111111111111111111111111111111 /
1&
#5600
0&
#5610
1$
1+
1&
#5620
0&
#5630
0$
0+
b111001 -
b111111111111111111111111111111111111111111111111111111111 /
1&
#5640
0&
#5650
1$
1+
1&
#5660
0&
#5670
0$
0+
b111010 -
b1111111111111111111111111111111111111111111111111111111111 /
1&
#5680
0&
#5690
1$
1+
1&
#5700
0&
#5710
0$
0+
b111011 -
b11111111111111111111111111111111111111111111111111111111111 /
1&
#5720
0&
#5730
1$
1+
1&
#5740
0&
#5750
0$
0+
b111100 -
b111111111111111111111111111111111111111111111111111111111111 /
1&
#5760
0&
#5770
1$
1+
1&
#5780
0&
#5790
0$
0+
b111101 -
b1111111111111111111111111111111111111111111111111111111111111 /
1&
#5800
0&
#5810
1$
1+
1&
#5820
0&
#5830
0$
0+
b111110 -
b11111111111111111111111111111111111111111111111111111111111111 /
1&
#5840
0&
#5850
1$
1+
1&
#5860
0&
#5870
0$
0+
b111111 -
b111111111111111111111111111111111111111111111111111111111111111 /
1&
#5880
0&
#5890
b11111111111111111111111111111111 "
b111111111111111111111111111111111111111111111111111111111111111 .
1$
1+
1&
#5900
0&
#5910
0$
0+
b0 -
b0 /
1&
#5920
0&
#5930
1$
1+
0#
0,
1&
#5940
0&
#5950
0$
0+
b1 -
b1 /
1&
#5960
0&
#5970
1$
1+
1&
#5980
0&
#5990
0$
0+
b10 -
b11 /
1&
#6000
0&
#6010
1$
1+
1&
#6020
0&
#6030
0$
0+
b11 -
b111 /
1&
#6040
0&
#6050
1$
1+
1&
#6060
0&
#6070
0$
0+
b100 -
b1111 /
1&
#6080
0&
#6090
1$
1+
1&
#6100
0&
#6110
0$
0+
b101 -
b11111 /
1&
#6120
0&
#6130
1$
1+
1&
#6140
0&
#6150
0$
0+
b110 -
b111111 /
1&
#6160
0&
#6170
1$
1+
1&
#6180
0&
#6190
0$
0+
b111 -
b1111111 /
1&
#6200
0&
#6210
1$
1+
1&
#6220
0&
#6230
0$
0+
b1000 -
b11111111 /
1&
#6240
0&
#6250
1$
1+
1&
#6260
0&
#6270
0$
0+
b1001 -
b111111111 /
1&
#6280
0&
#6290
1$
1+
1&
#6300
0&
#6310
0$
0+
b1010 -
b1111111111 /
1&
#6320
0&
#6330
1$
1+
1&
#6340
0&
#6350
0$
0+
b1011 -
b11111111111 /
1&
#6360
0&
#6370
1$
1+
1&
#6380
0&
#6390
0$
0+
b1100 -
b111111111111 /
1&
#6400
0&
#6410
1$
1+
1&
#6420
0&
#6430
0$
0+
b1101 -
b1111111111111 /
1&
#6440
0&
#6450
1$
1+
1&
#6460
0&
#6470
0$
0+
b1110 -
b11111111111111 /
1&
#6480
0&
#6490
1$
1+
1&
#6500
0&
#6510
0$
0+
b1111 -
b111111111111111 /
1&
#6520
0&
#6530
1$
1+
1&
#6540
0&
#6550
0$
0+
b10000 -
b1111111111111111 /
1&
#6560
0&
#6570
1$
1+
1&
#6580
0&
#6590
0$
0+
b10001 -
b11111111111111111 /
1&
#6600
0&
#6610
1$
1+
1&
#6620
0&
#6630
0$
0+
b10010 -
b111111111111111111 /
1&
#6640
0&
#6650
1$
1+
1&
#6660
0&
#6670
0$
0+
b10011 -
b1111111111111111111 /
1&
#6680
0&
#6690
1$
1+
1&
#6700
0&
#6710
0$
0+
b10100 -
b11111111111111111111 /
1&
#6720
0&
#6730
1$
1+
1&
#6740
0&
#6750
0$
0+
b10101 -
b111111111111111111111 /
1&
#6760
0&
#6770
1$
1+
1&
#6780
0&
#6790
0$
0+
b10110 -
b1111111111111111111111 /
1&
#6800
0&
#6810
1$
1+
1&
#6820
0&
#6830
0$
0+
b10111 -
b11111111111111111111111 /
1&
#6840
0&
#6850
1$
1+
1&
#6860
0&
#6870
0$
0+
b11000 -
b111111111111111111111111 /
1&
#6880
0&
#6890
1$
1+
1&
#6900
0&
#6910
0$
0+
b11001 -
b1111111111111111111111111 /
1&
#6920
0&
#6930
1$
1+
1&
#6940
0&
#6950
0$
0+
b11010 -
b11111111111111111111111111 /
1&
#6960
0&
#6970
1$
1+
1&
#6980
0&
#6990
0$
0+
b11011 -
b111111111111111111111111111 /
1&
#7000
0&
#7010
1$
1+
1&
#7020
0&
#7030
0$
0+
b11100 -
b1111111111111111111111111111 /
1&
#7040
0&
#7050
1$
1+
1&
#7060
0&
#7070
0$
0+
b11101 -
b11111111111111111111111111111 /
1&
#7080
0&
#7090
1$
1+
1&
#7100
0&
#7110
0$
0+
b11110 -
b111111111111111111111111111111 /
1&
#7120
0&
#7130
1$
1+
1&
#7140
0&
#7150
0$
0+
b11111 -
b1111111111111111111111111111111 /
1&
#7160
0&
#7170
1$
1+
1&
#7180
0&
#7190
0$
0+
b100000 -
b11111111111111111111111111111111 /
1&
#7200
0&
#7210
1$
1+
1#
1,
1&
#7220
0&
#7230
0$
0+
b100001 -
b111111111111111111111111111111111 /
1&
#7240
0&
#7250
1$
1+
1&
#7260
0&
#7270
0$
0+
b100010 -
b1111111111111111111111111111111111 /
1&
#7280
0&
#7290
1$
1+
1&
#7300
0&
#7310
0$
0+
b100011 -
b11111111111111111111111111111111111 /
1&
#7320
0&
#7330
1$
1+
1&
#7340
0&
#7350
0$
0+
b100100 -
b111111111111111111111111111111111111 /
1&
#7360
0&
#7370
1$
1+
1&
#7380
0&
#7390
0$
0+
b100101 -
b1111111111111111111111111111111111111 /
1&
#7400
0&
#7410
1$
1+
1&
#7420
0&
#7430
0$
0+
b100110 -
b11111111111111111111111111111111111111 /
1&
#7440
0&
#7450
1$
1+
1&
#7460
0&
#7470
0$
0+
b100111 -
b111111111111111111111111111111111111111 /
1&
#7480
0&
#7490
1$
1+
1&
#7500
0&
#7510
0$
0+
b101000 -
b1111111111111111111111111111111111111111 /
1&
#7520
0&
#7530
1$
1+
1&
#7540
0&
#7550
0$
0+
b101001 -
b11111111111111111111111111111111111111111 /
1&
#7560
0&
#7570
1$
1+
1&
#7580
0&
#7590
0$
0+
b101010 -
b111111111111111111111111111111111111111111 /
1&
#7600
0&
#7610
1$
1+
1&
#7620
0&
#7630
0$
0+
b101011 -
b1111111111111111111111111111111111111111111 /
1&
#7640
0&
#7650
1$
1+
1&
#7660
0&
#7670
0$
0+
b101100 -
b11111111111111111111111111111111111111111111 /
1&
#7680
0&
#7690
1$
1+
1&
#7700
0&
#7710
0$
0+
b101101 -
b111111111111111111111111111111111111111111111 /
1&
#7720
0&
#7730
1$
1+
1&
#7740
0&
#7750
0$
0+
b101110 -
b1111111111111111111111111111111111111111111111 /
1&
#7760
0&
#7770
1$
1+
1&
#7780
0&
#7790
0$
0+
b101111 -
b11111111111111111111111111111111111111111111111 /
1&
#7800
0&
#7810
1$
1+
1&
#7820
0&
#7830
0$
0+
b110000 -
b111111111111111111111111111111111111111111111111 /
1&
#7840
0&
#7850
1$
1+
1&
#7860
0&
#7870
0$
0+
b110001 -
b1111111111111111111111111111111111111111111111111 /
1&
#7880
0&
#7890
1$
1+
1&
#7900
0&
#7910
0$
0+
b110010 -
b11111111111111111111111111111111111111111111111111 /
1&
#7920
0&
#7930
1$
1+
1&
#7940
0&
#7950
0$
0+
b110011 -
b111111111111111111111111111111111111111111111111111 /
1&
#7960
0&
#7970
1$
1+
1&
#7980
0&
#7990
0$
0+
b110100 -
b1111111111111111111111111111111111111111111111111111 /
1&
#8000
0&
#8010
1$
1+
1&
#8020
0&
#8030
0$
0+
b110101 -
b11111111111111111111111111111111111111111111111111111 /
1&
#8040
0&
#8050
1$
1+
1&
#8060
0&
#8070
0$
0+
b110110 -
b111111111111111111111111111111111111111111111111111111 /
1&
#8080
0&
#8090
1$
1+
1&
#8100
0&
#8110
0$
0+
b110111 -
b1111111111111111111111111111111111111111111111111111111 /
1&
#8120
0&
#8130
1$
1+
1&
#8140
0&
#8150
0$
0+
b111000 -
b11111111111111111111111111111111111111111111111111111111 /
1&
#8160
0&
#8170
1$
1+
1&
#8180
0&
#8190
0$
0+
b111001 -
b111111111111111111111111111111111111111111111111111111111 /
1&
#8200
0&
#8210
1$
1+
1&
#8220
0&
#8230
0$
0+
b111010 -
b1111111111111111111111111111111111111111111111111111111111 /
1&
#8240
0&
#8250
1$
1+
1&
#8260
0&
#8270
0$
0+
b111011 -
b11111111111111111111111111111111111111111111111111111111111 /
1&
#8280
0&
#8290
1$
1+
1&
#8300
0&
#8310
0$
0+
b111100 -
b111111111111111111111111111111111111111111111111111111111111 /
1&
#8320
0&
#8330
1$
1+
1&
#8340
0&
#8350
0$
0+
b111101 -
b1111111111111111111111111111111111111111111111111111111111111 /
1&
#8360
0&
#8370
1$
1+
1&
#8380
0&
#8390
0$
0+
b111110 -
b11111111111111111111111111111111111111111111111111111111111111 /
1&
#8400
0&
#8410
1$
1+
1&
#8420
0&
#8430
0$
0+
b111111 -
b111111111111111111111111111111111111111111111111111111111111111 /
1&
#8440
0&
#8450
1$
1+
1&
#8460
0&
#8470
0$
0+
b0 -
b0 /
1&
#8480
0&
#8490
1$
1+
0#
0,
1&
#8500
0&
#8510
0$
0+
b1 -
b1 /
1&
#8520
0&
#8530
1$
1+
1&
#8540
0&
#8550
0$
0+
b10 -
b11 /
1&
#8560
0&
#8570
1$
1+
1&
#8580
0&
#8590
0$
0+
b11 -
b111 /
1&
#8600
0&
#8610
1$
1+
1&
#8620
0&
#8630
0$
0+
b100 -
b1111 /
1&
#8640
0&
#8650
1$
1+
1&
#8660
0&
#8670
0$
0+
b101 -
b11111 /
1&
#8680
0&
#8690
1$
1+
1&
#8700
0&
#8710
0$
0+
b110 -
b111111 /
1&
#8720
0&
#8730
1$
1+
1&
#8740
0&
#8750
0$
0+
b111 -
b1111111 /
1&
#8760
0&
#8770
1$
1+
1&
#8780
0&
#8790
0$
0+
b1000 -
b11111111 /
1&
#8800
0&
#8810
1$
1+
1&
#8820
0&
#8830
0$
0+
b1001 -
b111111111 /
1&
#8840
0&
#8850
1$
1+
1&
#8860
0&
#8870
0$
0+
b1010 -
b1111111111 /
1&
#8880
0&
#8890
1$
1+
1&
#8900
0&
#8910
0$
0+
b1011 -
b11111111111 /
1&
#8920
0&
#8930
1$
1+
1&
#8940
0&
#8950
0$
0+
b1100 -
b111111111111 /
1&
#8960
0&
#8970
1$
1+
1&
#8980
0&
#8990
0$
0+
b1101 -
b1111111111111 /
1&
#9000
0&
#9010
1$
1+
1&
#9020
0&
#9030
0$
0+
b1110 -
b11111111111111 /
1&
#9040
0&
#9050
1$
1+
1&
#9060
0&
#9070
0$
0+
b1111 -
b111111111111111 /
1&
#9080
0&
#9090
1$
1+
1&
#9100
0&
#9110
0$
0+
b10000 -
b1111111111111111 /
1&
#9120
0&
#9130
1$
1+
1&
#9140
0&
#9150
0$
0+
b10001 -
b11111111111111111 /
1&
#9160
0&
#9170
1$
1+
1&
#9180
0&
#9190
0$
0+
b10010 -
b111111111111111111 /
1&
#9200
0&
#9210
1$
1+
1&
#9220
0&
#9230
0$
0+
b10011 -
b1111111111111111111 /
1&
#9240
0&
#9250
1$
1+
1&
#9260
0&
#9270
0$
0+
b10100 -
b11111111111111111111 /
1&
#9280
0&
#9290
1$
1+
1&
#9300
0&
#9310
0$
0+
b10101 -
b111111111111111111111 /
1&
#9320
0&
#9330
1$
1+
1&
#9340
0&
#9350
0$
0+
b10110 -
b1111111111111111111111 /
1&
#9360
0&
#9370
1$
1+
1&
#9380
0&
#9390
0$
0+
b10111 -
b11111111111111111111111 /
1&
#9400
0&
#9410
1$
1+
1&
#9420
0&
#9430
0$
0+
b11000 -
b111111111111111111111111 /
1&
#9440
0&
#9450
1$
1+
1&
#9460
0&
#9470
0$
0+
b11001 -
b1111111111111111111111111 /
1&
#9480
0&
#9490
1$
1+
1&
#9500
0&
#9510
0$
0+
b11010 -
b11111111111111111111111111 /
1&
#9520
0&
#9530
1$
1+
1&
#9540
0&
#9550
0$
0+
b11011 -
b111111111111111111111111111 /
1&
#9560
0&
#9570
1$
1+
1&
#9580
0&
#9590
0$
0+
b11100 -
b1111111111111111111111111111 /
1&
#9600
0&
#9610
1$
1+
1&
#9620
0&
#9630
0$
0+
b11101 -
b11111111111111111111111111111 /
1&
#9640
0&
#9650
1$
1+
1&
#9660
0&
