Lab8_microphone/rtl/i2s/i2s_test.v


module i2s_test (
    input WS,
    input BCLK,
    output DIN,
    input en, 
    input rst_n
);
    reg [31:0] test_array [7:0];  // Array for storing 32-bit values

    initial begin
        $readmemh("/home/seif/dev/projects/tinyml-soc/Lab8_microphone/rtl/i2s/test.hex", test_array);  // Load data from test.hex file
    end

    integer i = 0;
    integer j = 0;

    reg DIN_d;

    always @(negedge BCLK, negedge rst_n) begin
        if (!rst_n) begin
            DIN_d <= 0;
            i = 0;
            j = 0;
        end
        else
        if (!WS && en) begin
            DIN_d = test_array[j][31-i];  // Access each bit in the 32-bit word
            //print din_d;
            //$display("DIN_d: %b %h %d %d", DIN, test_array[j], i, j);
            //DIN_d<=1;
        end

        // Increment i and reset when it reaches 31
        if(en && !WS) begin
        if (i == 31) begin
            i = 0;
            j = (j + 1) % 8;  // Reset j to 0 after reaching 7
            $display("j: %d", j);
        end else begin
            i = i + 1;
        end
        end
    end

    assign DIN = DIN_d;
endmodule

Lab8_microphone/rtl/i2s/i2s.v
module i2s(
    input clk,
    input rst_n,
    output WS,
    output BCLK,
    input DIN,
    output reg done,
    output reg [size -1:0] data,
    input en,
    input ack_data,
    input ack_done
);

reg BCLK_d, WS_d;
localparam size = 32;
reg [$clog2(size) -1:0] bit_count;
reg [size -1 : 0] shift_reg;
reg [5:0] WS_cntr;
reg [1:0] BCLK_cntr;
wire WS_cntr_zero = WS_cntr == 6'b000000;
wire cntr_two = BCLK_cntr == 2'b10;
// WS
always @(posedge clk, negedge rst_n) begin
    if(!rst_n) begin
        WS_d <= 0;
    end
    else if(en) begin
        if(WS_cntr_zero && cntr_two) begin
            WS_d <= !WS_d;
        end
    end
end

// WS counter

always @(posedge clk, negedge rst_n) begin
    if(!rst_n) begin
        WS_cntr <= 0;
    end
    else if(en) begin
        if (cntr_two) begin
            WS_cntr <= WS_cntr + 1;
        end
    end
end

// BCLK

always @(posedge clk, negedge rst_n) begin
    if (!rst_n) begin
        BCLK_d <= 0;
    end
    else if(en) begin
        if(cntr_two) begin
            BCLK_d <= ~BCLK_d;
        end
    end
end

// bclk counter

always@(posedge clk, negedge rst_n) begin
    if(!rst_n) begin
        BCLK_cntr <= 0;
    end
    else if(en) begin
        if(cntr_two) begin
            BCLK_cntr <= 0;
        end
        else BCLK_cntr <= BCLK_cntr + 1;
    end
end


// shift register

always @(posedge clk, negedge rst_n) begin
     if (!rst_n) begin
        shift_reg <= 32'd0;
    end
    else if(en) begin
        if(!WS && BCLK_cntr == 0 && !BCLK) begin 
            shift_reg <= {shift_reg[size -2 : 0],DIN};
        end
    end
end


// done
always @(posedge clk, negedge rst_n) begin
    if (!rst_n) begin
        done <= 0;
    end
    else if(en) begin
        if(WS_cntr_zero) begin
            done <= 1;
        end
        else if(ack_done) begin
            done <= 0;
        end
    end
end

// data
always @(posedge clk, negedge rst_n) begin
    if (!rst_n) begin
        data <= 0;
    end
    else if(en) begin
        if(WS_cntr_zero) begin
            data <= shift_reg;
        end
        else if(ack_data) begin
            data <= shift_reg;
        end
    end
end

assign WS = WS_d;
assign BCLK = BCLK_d;


endmodule

Lab9_interupts/rtl/i2s/i2s_tb.v
module i2s_tb;
    reg clk = 0;
    reg rst_n = 0;
    wire WS;
    wire BCLK;
    wire DIN;
    wire done;
    wire [31:0] data;
    reg en;
    reg [5:0] counter;

    i2s duv (
        .clk(clk),
        .rst_n(rst_n),
        .WS(WS),
        .BCLK(BCLK),
        .DIN(DIN),
        .done(done),
        .data(data),
        .en(en)
    );

    i2s_test tb (
        .WS(WS),
        .BCLK(BCLK),
        .DIN(DIN),
        .en(en),
        .rst_n(rst_n)
    );

    always #10 clk = !clk;

    initial begin
        #777;
        @(posedge clk);
        #1; 
        rst_n = 1;
    end

    initial begin
        $dumpfile("i2s_tb.vcd");
        $dumpvars;
    end

    initial begin
        en = 0;
        wait(rst_n == 1'b1);
        @(posedge clk);
        en = 1;
        #100000;
        $finish;
    end

    // always@(posedge clk or WS) begin
    //     if(WS) 
    //         DIN = 1;
    // end




endmodule

Lab8_microphone/rtl/i2s/i2s_tb.vcd
$date
	Tue Nov  5 19:13:01 2024
$end
$version
	Icarus Verilog
$end
$timescale
	1s
$end
$scope module i2s_tb $end
$var wire 1 ! done $end
$var wire 32 " data [31:0] $end
$var wire 1 # WS $end
$var wire 1 $ DIN $end
$var wire 1 % BCLK $end
$var reg 1 & clk $end
$var reg 1 ' en $end
$var reg 1 ( rst_n $end
$scope module duv $end
$var wire 1 % BCLK $end
$var wire 1 # WS $end
$var wire 1 ) ack_data $end
$var wire 1 * ack_done $end
$var wire 1 & clk $end
$var wire 1 ' en $end
$var wire 1 ( rst_n $end
$var wire 1 + cntr_two $end
$var wire 1 , WS_cntr_zero $end
$var wire 1 $ DIN $end
$var reg 2 - BCLK_cntr [1:0] $end
$var reg 1 . BCLK_d $end
$var reg 6 / WS_cntr [5:0] $end
$var reg 1 0 WS_d $end
$var reg 32 1 data [31:0] $end
$var reg 1 ! done $end
$var reg 32 2 shift_reg [31:0] $end
$upscope $end
$scope module tb $end
$var wire 1 % BCLK $end
$var wire 1 $ DIN $end
$var wire 1 # WS $end
$var wire 1 ' en $end
$var wire 1 ( rst_n $end
$var reg 1 3 DIN_d $end
$var integer 32 4 i [31:0] $end
$var integer 32 5 j [31:0] $end
$upscope $end
$upscope $end
$enddefinitions $end
#0
$dumpvars
b0 5
b0 4
03
b0 2
b0 1
00
b0 /
0.
b0 -
1,
0+
z*
z)
0(
0'
0&
0%
0$
0#
b0 "
0!
$end
#10
1&
#20
0&
#30
1&
#40
0&
#50
1&
#60
0&
#70
1&
#80
0&
#90
1&
#100
0&
#110
1&
#120
0&
#130
1&
#140
0&
#150
1&
#160
0&
#170
1&
#180
0&
#190
1&
#200
0&
#210
1&
#220
0&
#230
1&
#240
0&
#250
1&
#260
0&
#270
1&
#280
0&
#290
1&
#300
0&
#310
1&
#320
0&
#330
1&
#340
0&
#350
1&
#360
0&
#370
1&
#380
0&
#390
1&
#400
0&
#410
1&
#420
0&
#430
1&
#440
0&
#450
1&
#460
0&
#470
1&
#480
0&
#490
1&
#500
0&
#510
1&
#520
0&
#530
1&
#540
0&
#550
1&
#560
0&
#570
1&
#580
0&
#590
1&
#600
0&
#610
1&
#620
0&
#630
1&
#640
0&
#650
1&
#660
0&
#670
1&
#680
0&
#690
1&
#700
0&
#710
1&
#720
0&
#730
1&
#740
0&
#750
1&
#760
0&
#770
1&
#780
0&
#790
1&
#791
1(
#800
0&
#810
1!
b1 -
1'
1&
#820
0&
#830
1+
b10 -
1&
#840
0&
#850
0+
b0 -
1%
1.
0,
b1 /
1#
10
1&
#860
0&
#870
b1 -
1&
#880
0&
#890
1+
b10 -
1&
#900
0&
#910
b10 /
0%
0.
0+
b0 -
1&
#920
0&
#930
b1 -
1&
#940
0&
#950
1+
b10 -
1&
#960
0&
#970
0+
b0 -
1%
1.
b11 /
1&
#980
0&
#990
b1 -
1&
#1000
0&
#1010
1+
b10 -
1&
#1020
0&
#1030
b100 /
0%
0.
0+
b0 -
1&
#1040
0&
#1050
b1 -
1&
#1060
0&
#1070
1+
b10 -
1&
#1080
0&
#1090
0+
b0 -
1%
1.
b101 /
1&
#1100
0&
#1110
b1 -
1&
#1120
0&
#1130
1+
b10 -
1&
#1140
0&
#1150
b110 /
0%
0.
0+
b0 -
1&
#1160
0&
#1170
b1 -
1&
#1180
0&
#1190
1+
b10 -
1&
#1200
0&
#1210
0+
b0 -
1%
1.
b111 /
1&
#1220
0&
#1230
b1 -
1&
#1240
0&
#1250
1+
b10 -
1&
#1260
0&
#1270
b1000 /
0%
0.
0+
b0 -
1&
#1280
0&
#1290
b1 -
1&
#1300
0&
#1310
1+
b10 -
1&
#1320
0&
#1330
0+
b0 -
1%
1.
b1001 /
1&
#1340
0&
#1350
b1 -
1&
#1360
0&
#1370
1+
b10 -
1&
#1380
0&
#1390
b1010 /
0%
0.
0+
b0 -
1&
#1400
0&
#1410
b1 -
1&
#1420
0&
#1430
1+
b10 -
1&
#1440
0&
#1450
0+
b0 -
1%
1.
b1011 /
1&
#1460
0&
#1470
b1 -
1&
#1480
0&
#1490
1+
b10 -
1&
#1500
0&
#1510
b1100 /
0%
0.
0+
b0 -
1&
#1520
0&
#1530
b1 -
1&
#1540
0&
#1550
1+
b10 -
1&
#1560
0&
#1570
0+
b0 -
1%
1.
b1101 /
1&
#1580
0&
#1590
b1 -
1&
#1600
0&
#1610
1+
b10 -
1&
#1620
0&
#1630
b1110 /
0%
0.
0+
b0 -
1&
#1640
0&
#1650
b1 -
1&
#1660
0&
#1670
1+
b10 -
1&
#1680
0&
#1690
0+
b0 -
1%
1.
b1111 /
1&
#1700
0&
#1710
b1 -
1&
#1720
0&
#1730
1+
b10 -
1&
#1740
0&
#1750
b10000 /
0%
0.
0+
b0 -
1&
#1760
0&
#1770
b1 -
1&
#1780
0&
#1790
1+
b10 -
1&
#1800
0&
#1810
0+
b0 -
1%
1.
b10001 /
1&
#1820
0&
#1830
b1 -
1&
#1840
0&
#1850
1+
b10 -
1&
#1860
0&
#1870
b10010 /
0%
0.
0+
b0 -
1&
#1880
0&
#1890
b1 -
1&
#1900
0&
#1910
1+
b10 -
1&
#1920
0&
#1930
0+
b0 -
1%
1.
b10011 /
1&
#1940
0&
#1950
b1 -
1&
#1960
0&
#1970
1+
b10 -
1&
#1980
0&
#1990
b10100 /
0%
0.
0+
b0 -
1&
#2000
0&
#2010
b1 -
1&
#2020
0&
#2030
1+
b10 -
1&
#2040
0&
#2050
0+
b0 -
1%
1.
b10101 /
1&
#2060
0&
#2070
b1 -
1&
#2080
0&
#2090
1+
b10 -
1&
#2100
0&
#2110
b10110 /
0%
0.
0+
b0 -
1&
#2120
0&
#2130
b1 -
1&
#2140
0&
#2150
1+
b10 -
1&
#2160
0&
#2170
0+
b0 -
1%
1.
b10111 /
1&
#2180
0&
#2190
b1 -
1&
#2200
0&
#2210
1+
b10 -
1&
#2220
0&
#2230
b11000 /
0%
0.
0+
b0 -
1&
#2240
0&
#2250
b1 -
1&
#2260
0&
#2270
1+
b10 -
1&
#2280
0&
#2290
0+
b0 -
1%
1.
b11001 /
1&
#2300
0&
#2310
b1 -
1&
#2320
0&
#2330
1+
b10 -
1&
#2340
0&
#2350
b11010 /
0%
0.
0+
b0 -
1&
#2360
0&
#2370
b1 -
1&
#2380
0&
#2390
1+
b10 -
1&
#2400
0&
#2410
0+
b0 -
1%
1.
b11011 /
1&
#2420
0&
#2430
b1 -
1&
#2440
0&
#2450
1+
b10 -
1&
#2460
0&
#2470
b11100 /
0%
0.
0+
b0 -
1&
#2480
0&
#2490
b1 -
1&
#2500
0&
#2510
1+
b10 -
1&
#2520
0&
#2530
0+
b0 -
1%
1.
b11101 /
1&
#2540
0&
#2550
b1 -
1&
#2560
0&
#2570
1+
b10 -
1&
#2580
0&
#2590
b11110 /
0%
0.
0+
b0 -
1&
#2600
0&
#2610
b1 -
1&
#2620
0&
#2630
1+
b10 -
1&
#2640
0&
#2650
0+
b0 -
1%
1.
b11111 /
1&
#2660
0&
#2670
b1 -
1&
#2680
0&
#2690
1+
b10 -
1&
#2700
0&
#2710
b100000 /
0%
0.
0+
b0 -
1&
#2720
0&
#2730
b1 -
1&
#2740
0&
#2750
1+
b10 -
1&
#2760
0&
#2770
0+
b0 -
1%
1.
b100001 /
1&
#2780
0&
#2790
b1 -
1&
#2800
0&
#2810
1+
b10 -
1&
#2820
0&
#2830
b100010 /
0%
0.
0+
b0 -
1&
#2840
0&
#2850
b1 -
1&
#2860
0&
#2870
1+
b10 -
1&
#2880
0&
#2890
0+
b0 -
1%
1.
b100011 /
1&
#2900
0&
#2910
b1 -
1&
#2920
0&
#2930
1+
b10 -
1&
#2940
0&
#2950
b100100 /
0%
0.
0+
b0 -
1&
#2960
0&
#2970
b1 -
1&
#2980
0&
#2990
1+
b10 -
1&
#3000
0&
#3010
0+
b0 -
1%
1.
b100101 /
1&
#3020
0&
#3030
b1 -
1&
#3040
0&
#3050
1+
b10 -
1&
#3060
0&
#3070
b100110 /
0%
0.
0+
b0 -
1&
#3080
0&
#3090
b1 -
1&
#3100
0&
#3110
1+
b10 -
1&
#3120
0&
#3130
0+
b0 -
1%
1.
b100111 /
1&
#3140
0&
#3150
b1 -
1&
#3160
0&
#3170
1+
b10 -
1&
#3180
0&
#3190
b101000 /
0%
0.
0+
b0 -
1&
#3200
0&
#3210
b1 -
1&
#3220
0&
#3230
1+
b10 -
1&
#3240
0&
#3250
0+
b0 -
1%
1.
b101001 /
1&
#3260
0&
#3270
b1 -
1&
#3280
0&
#3290
1+
b10 -
1&
#3300
0&
#3310
b101010 /
0%
0.
0+
b0 -
1&
#3320
0&
#3330
b1 -
1&
#3340
0&
#3350
1+
b10 -
1&
#3360
0&
#3370
0+
b0 -
1%
1.
b101011 /
1&
#3380
0&
#3390
b1 -
1&
#3400
0&
#3410
1+
b10 -
1&
#3420
0&
#3430
b101100 /
0%
0.
0+
b0 -
1&
#3440
0&
#3450
b1 -
1&
#3460
0&
#3470
1+
b10 -
1&
#3480
0&
#3490
0+
b0 -
1%
1.
b101101 /
1&
#3500
0&
#3510
b1 -
1&
#3520
0&
#3530
1+
b10 -
1&
#3540
0&
#3550
b101110 /
0%
0.
0+
b0 -
1&
#3560
0&
#3570
b1 -
1&
#3580
0&
#3590
1+
b10 -
1&
#3600
0&
#3610
0+
b0 -
1%
1.
b101111 /
1&
#3620
0&
#3630
b1 -
1&
#3640
0&
#3650
1+
b10 -
1&
#3660
0&
#3670
b110000 /
0%
0.
0+
b0 -
1&
#3680
0&
#3690
b1 -
1&
#3700
0&
#3710
1+
b10 -
1&
#3720
0&
#3730
0+
b0 -
1%
1.
b110001 /
1&
#3740
0&
#3750
b1 -
1&
#3760
0&
#3770
1+
b10 -
1&
#3780
0&
#3790
b110010 /
0%
0.
0+
b0 -
1&
#3800
0&
#3810
b1 -
1&
#3820
0&
#3830
1+
b10 -
1&
#3840
0&
#3850
0+
b0 -
1%
1.
b110011 /
1&
#3860
0&
#3870
b1 -
1&
#3880
0&
#3890
1+
b10 -
1&
#3900
0&
#3910
b110100 /
0%
0.
0+
b0 -
1&
#3920
0&
#3930
b1 -
1&
#3940
0&
#3950
1+
b10 -
1&
#3960
0&
#3970
0+
b0 -
1%
1.
b110101 /
1&
#3980
0&
#3990
b1 -
1&
#4000
0&
#4010
1+
b10 -
1&
#4020
0&
#4030
b110110 /
0%
0.
0+
b0 -
1&
#4040
0&
#4050
b1 -
1&
#4060
0&
#4070
1+
b10 -
1&
#4080
0&
#4090
0+
b0 -
1%
1.
b110111 /
1&
#4100
0&
#4110
b1 -
1&
#4120
0&
#4130
1+
b10 -
1&
#4140
0&
#4150
b111000 /
0%
0.
0+
b0 -
1&
#4160
0&
#4170
b1 -
1&
#4180
0&
#4190
1+
b10 -
1&
#4200
0&
#4210
0+
b0 -
1%
1.
b111001 /
1&
#4220
0&
#4230
b1 -
1&
#4240
0&
#4250
1+
b10 -
1&
#4260
0&
#4270
b111010 /
0%
0.
0+
b0 -
1&
#4280
0&
#4290
b1 -
1&
#4300
0&
#4310
1+
b10 -
1&
#4320
0&
#4330
0+
b0 -
1%
1.
b111011 /
1&
#4340
0&
#4350
b1 -
1&
#4360
0&
#4370
1+
b10 -
1&
#4380
0&
#4390
b111100 /
0%
0.
0+
b0 -
1&
#4400
0&
#4410
b1 -
1&
#4420
0&
#4430
1+
b10 -
1&
#4440
0&
#4450
0+
b0 -
1%
1.
b111101 /
1&
#4460
0&
#4470
b1 -
1&
#4480
0&
#4490
1+
b10 -
1&
#4500
0&
#4510
b111110 /
0%
0.
0+
b0 -
1&
#4520
0&
#4530
b1 -
1&
#4540
0&
#4550
1+
b10 -
1&
#4560
0&
#4570
0+
b0 -
1%
1.
b111111 /
1&
#4580
0&
#4590
b1 -
1&
#4600
0&
#4610
1+
b10 -
1&
#4620
0&
#4630
1,
b0 /
0%
0.
0+
b0 -
1&
#4640
0&
#4650
b1 -
1&
#4660
0&
#4670
1+
b10 -
1&
#4680
0&
#4690
0+
b0 -
1%
1.
0,
b1 /
0#
00
1&
#4700
0&
#4710
b1 -
1&
#4720
0&
#4730
1+
b10 -
1&
#4740
0&
#4750
b1 4
b10 /
0%
0.
0+
b0 -
1&
#4760
0&
#4770
b1 -
1&
#4780
0&
#4790
1+
b10 -
1&
#4800
0&
#4810
0+
b0 -
1%
1.
b11 /
1&
#4820
0&
#4830
b1 -
1&
#4840
0&
#4850
1+
b10 -
1&
#4860
0&
#4870
b10 4
1$
13
b100 /
0%
0.
0+
b0 -
1&
#4880
0&
#4890
b1 2
b1 -
1&
#4900
0&
#4910
1+
b10 -
1&
#4920
0&
#4930
0+
b0 -
1%
1.
b101 /
1&
#4940
0&
#4950
b1 -
1&
#4960
0&
#4970
1+
b10 -
1&
#4980
0&
#4990
b11 4
0$
03
b110 /
0%
0.
0+
b0 -
1&
#5000
0&
#5010
b10 2
b1 -
1&
#5020
0&
#5030
1+
b10 -
1&
#5040
0&
#5050
0+
b0 -
1%
1.
b111 /
1&
#5060
0&
#5070
b1 -
1&
#5080
0&
#5090
1+
b10 -
1&
#5100
0&
#5110
b100 4
b1000 /
0%
0.
0+
b0 -
1&
#5120
0&
#5130
b100 2
b1 -
1&
#5140
0&
#5150
1+
b10 -
1&
#5160
0&
#5170
0+
b0 -
1%
1.
b1001 /
1&
#5180
0&
#5190
b1 -
1&
#5200
0&
#5210
1+
b10 -
1&
#5220
0&
#5230
b101 4
b1010 /
0%
0.
0+
b0 -
1&
#5240
0&
#5250
b1000 2
b1 -
1&
#5260
0&
#5270
1+
b10 -
1&
#5280
0&
#5290
0+
b0 -
1%
1.
b1011 /
1&
#5300
0&
#5310
b1 -
1&
#5320
0&
#5330
1+
b10 -
1&
#5340
0&
#5350
b110 4
b1100 /
0%
0.
0+
b0 -
1&
#5360
0&
#5370
b10000 2
b1 -
1&
#5380
0&
#5390
1+
b10 -
1&
#5400
0&
#5410
0+
b0 -
1%
1.
b1101 /
1&
#5420
0&
#5430
b1 -
1&
#5440
0&
#5450
1+
b10 -
1&
#5460
0&
#5470
b111 4
b1110 /
0%
0.
0+
b0 -
1&
#5480
0&
#5490
b100000 2
b1 -
1&
#5500
0&
#5510
1+
b10 -
1&
#5520
0&
#5530
0+
b0 -
1%
1.
b1111 /
1&
#5540
0&
#5550
b1 -
1&
#5560
0&
#5570
1+
b10 -
1&
#5580
0&
#5590
b1000 4
b10000 /
0%
0.
0+
b0 -
1&
#5600
0&
#5610
b1000000 2
b1 -
1&
#5620
0&
#5630
1+
b10 -
1&
#5640
0&
#5650
0+
b0 -
1%
1.
b10001 /
1&
#5660
0&
#5670
b1 -
1&
#5680
0&
#5690
1+
b10 -
1&
#5700
0&
#5710
b1001 4
1$
13
b10010 /
0%
0.
0+
b0 -
1&
#5720
0&
#5730
b10000001 2
b1 -
1&
#5740
0&
#5750
1+
b10 -
1&
#5760
0&
#5770
0+
b0 -
1%
1.
b10011 /
1&
#5780
0&
#5790
b1 -
1&
#5800
0&
#5810
1+
b10 -
1&
#5820
0&
#5830
b1010 4
0$
03
b10100 /
0%
0.
0+
b0 -
1&
#5840
0&
#5850
b100000010 2
b1 -
1&
#5860
0&
#5870
1+
b10 -
1&
#5880
0&
#5890
0+
b0 -
1%
1.
b10101 /
1&
#5900
0&
#5910
b1 -
1&
#5920
0&
#5930
1+
b10 -
1&
#5940
0&
#5950
b1011 4
1$
13
b10110 /
0%
0.
0+
b0 -
1&
#5960
0&
#5970
b1000000101 2
b1 -
1&
#5980
0&
#5990
1+
b10 -
1&
#6000
0&
#6010
0+
b0 -
1%
1.
b10111 /
1&
#6020
0&
#6030
b1 -
1&
#6040
0&
#6050
1+
b10 -
1&
#6060
0&
#6070
b1100 4
0$
03
b11000 /
0%
0.
0+
b0 -
1&
#6080
0&
#6090
b10000001010 2
b1 -
1&
#6100
0&
#6110
1+
b10 -
1&
#6120
0&
#6130
0+
b0 -
1%
1.
b11001 /
1&
#6140
0&
#6150
b1 -
1&
#6160
0&
#6170
1+
b10 -
1&
#6180
0&
#6190
b1101 4
1$
13
b11010 /
0%
0.
0+
b0 -
1&
#6200
0&
#6210
b100000010101 2
b1 -
1&
#6220
0&
#6230
1+
b10 -
1&
#6240
0&
#6250
0+
b0 -
1%
1.
b11011 /
1&
#6260
0&
#6270
b1 -
1&
#6280
0&
#6290
1+
b10 -
1&
#6300
0&
#6310
b1110 4
0$
03
b11100 /
0%
0.
0+
b0 -
1&
#6320
0&
#6330
b1000000101010 2
b1 -
1&
#6340
0&
#6350
1+
b10 -
1&
#6360
0&
#6370
0+
b0 -
1%
1.
b11101 /
1&
#6380
0&
#6390
b1 -
1&
#6400
0&
#6410
1+
b10 -
1&
#6420
0&
#6430
b1111 4
b11110 /
0%
0.
0+
b0 -
1&
#6440
0&
#6450
b10000001010100 2
b1 -
1&
#6460
0&
#6470
1+
b10 -
1&
#6480
0&
#6490
0+
b0 -
1%
1.
b11111 /
1&
#6500
0&
#6510
b1 -
1&
#6520
0&
#6530
1+
b10 -
1&
#6540
0&
#6550
b10000 4
b100000 /
0%
0.
0+
b0 -
1&
#6560
0&
#6570
b100000010101000 2
b1 -
1&
#6580
0&
#6590
1+
b10 -
1&
#6600
0&
#6610
0+
b0 -
1%
1.
b100001 /
1&
#6620
0&
#6630
b1 -
1&
#6640
0&
#6650
1+
b10 -
1&
#6660
0&
#6670
b10001 4
1$
13
b100010 /
0%
0.
0+
b0 -
1&
#6680
0&
#6690
b1000000101010001 2
b1 -
1&
#6700
0&
#6710
1+
b10 -
1&
#6720
0&
#6730
0+
b0 -
1%
1.
b100011 /
1&
#6740
0&
#6750
b1 -
1&
#6760
0&
#6770
1+
b10 -
1&
#6780
0&
#6790
b10010 4
b100100 /
0%
0.
0+
b0 -
1&
#6800
0&
#6810
b10000001010100011 2
b1 -
1&
#6820
0&
#6830
1+
b10 -
1&
#6840
0&
#6850
0+
b0 -
1%
1.
b100101 /
1&
#6860
0&
#6870
b1 -
1&
#6880
0&
#6890
1+
b10 -
1&
#6900
0&
#6910
b10011 4
b100110 /
0%
0.
0+
b0 -
1&
#6920
0&
#6930
b100000010101000111 2
b1 -
1&
#6940
0&
#6950
1+
b10 -
1&
#6960
0&
#6970
0+
b0 -
1%
1.
b100111 /
1&
#6980
0&
#6990
b1 -
1&
#7000
0&
#7010
1+
b10 -
1&
#7020
0&
#7030
b10100 4
0$
03
b101000 /
0%
0.
0+
b0 -
1&
#7040
0&
#7050
b1000000101010001110 2
b1 -
1&
#7060
0&
#7070
1+
b10 -
1&
#7080
0&
#7090
0+
b0 -
1%
1.
b101001 /
1&
#7100
0&
#7110
b1 -
1&
#7120
0&
#7130
1+
b10 -
1&
#7140
0&
#7150
b10101 4
b101010 /
0%
0.
0+
b0 -
1&
#7160
0&
#7170
b10000001010100011100 2
b1 -
1&
#7180
0&
#7190
1+
b10 -
1&
#7200
0&
#7210
0+
b0 -
1%
1.
b101011 /
1&
#7220
0&
#7230
b1 -
1&
#7240
0&
#7250
1+
b10 -
1&
#7260
0&
#7270
b10110 4
1$
13
b101100 /
0%
0.
0+
b0 -
1&
#7280
0&
#7290
b100000010101000111001 2
b1 -
1&
#7300
0&
#7310
1+
b10 -
1&
#7320
0&
#7330
0+
b0 -
1%
1.
b101101 /
1&
#7340
0&
#7350
b1 -
1&
#7360
0&
#7370
1+
b10 -
1&
#7380
0&
#7390
b10111 4
0$
03
b101110 /
0%
0.
0+
b0 -
1&
#7400
0&
#7410
b1000000101010001110010 2
b1 -
1&
#7420
0&
#7430
1+
b10 -
1&
#7440
0&
#7450
0+
b0 -
1%
1.
b101111 /
1&
#7460
0&
#7470
b1 -
1&
#7480
0&
#7490
1+
b10 -
1&
#7500
0&
#7510
b11000 4
1$
13
b110000 /
0%
0.
0+
b0 -
1&
#7520
0&
#7530
b10000001010100011100101 2
b1 -
1&
#7540
0&
#7550
1+
b10 -
1&
#7560
0&
#7570
0+
b0 -
1%
1.
b110001 /
1&
#7580
0&
#7590
b1 -
1&
#7600
0&
#7610
1+
b10 -
1&
#7620
0&
#7630
b11001 4
b110010 /
0%
0.
0+
b0 -
1&
#7640
0&
#7650
b100000010101000111001011 2
b1 -
1&
#7660
0&
#7670
1+
b10 -
1&
#7680
0&
#7690
0+
b0 -
1%
1.
b110011 /
1&
#7700
0&
#7710
b1 -
1&
#7720
0&
#7730
1+
b10 -
1&
#7740
0&
#7750
b11010 4
0$
03
b110100 /
0%
0.
0+
b0 -
1&
#7760
0&
#7770
b1000000101010001110010110 2
b1 -
1&
#7780
0&
#7790
1+
b10 -
1&
#7800
0&
#7810
0+
b0 -
1%
1.
b110101 /
1&
#7820
0&
#7830
b1 -
1&
#7840
0&
#7850
1+
b10 -
1&
#7860
0&
#7870
b11011 4
b110110 /
0%
0.
0+
b0 -
1&
#7880
0&
#7890
b10000001010100011100101100 2
b1 -
1&
#7900
0&
#7910
1+
b10 -
1&
#7920
0&
#7930
0+
b0 -
1%
1.
b110111 /
1&
#7940
0&
#7950
b1 -
1&
#7960
0&
#7970
1+
b10 -
1&
#7980
0&
#7990
b11100 4
1$
13
b111000 /
0%
0.
0+
b0 -
1&
#8000
0&
#8010
b100000010101000111001011001 2
b1 -
1&
#8020
0&
#8030
1+
b10 -
1&
#8040
0&
#8050
0+
b0 -
1%
1.
b111001 /
1&
#8060
0&
#8070
b1 -
1&
#8080
0&
#8090
1+
b10 -
1&
#8100
0&
#8110
b11101 4
b111010 /
0%
0.
0+
b0 -
1&
#8120
0&
#8130
b1000000101010001110010110011 2
b1 -
1&
#8140
0&
#8150
1+
b10 -
1&
#8160
0&
#8170
0+
b0 -
1%
1.
b111011 /
1&
#8180
0&
#8190
b1 -
1&
#8200
0&
#8210
1+
b10 -
1&
#8220
0&
#8230
b11110 4
0$
03
b111100 /
0%
0.
0+
b0 -
1&
#8240
0&
#8250
b10000001010100011100101100110 2
b1 -
1&
#8260
0&
#8270
1+
b10 -
1&
#8280
0&
#8290
0+
b0 -
1%
1.
b111101 /
1&
#8300
0&
#8310
b1 -
1&
#8320
0&
#8330
1+
b10 -
1&
#8340
0&
#8350
b11111 4
b111110 /
0%
0.
0+
b0 -
1&
#8360
0&
#8370
b100000010101000111001011001100 2
b1 -
1&
#8380
0&
#8390
1+
b10 -
1&
#8400
0&
#8410
0+
b0 -
1%
1.
b111111 /
1&
#8420
0&
#8430
b1 -
1&
#8440
0&
#8450
1+
b10 -
1&
#8460
0&
#8470
b1 5
b0 4
1,
b0 /
0%
0.
0+
b0 -
1&
#8480
0&
#8490
b100000010101000111001011001100 "
b100000010101000111001011001100 1
b1000000101010001110010110011000 2
b1 -
1&
#8500
0&
#8510
1+
b10 -
b1000000101010001110010110011000 "
b1000000101010001110010110011000 1
1&
#8520
0&
#8530
0+
b0 -
1%
1.
0,
b1 /
1#
10
1&
#8540
0&
#8550
b1 -
1&
#8560
0&
#8570
1+
b10 -
1&
#8580
0&
#8590
b10 /
0%
0.
0+
b0 -
1&
#8600
0&
#8610
b1 -
1&
#8620
0&
#8630
1+
b10 -
1&
#8640
0&
#8650
0+
b0 -
1%
1.
b11 /
1&
#8660
0&
#8670
b1 -
1&
#8680
0&
#8690
1+
b10 -
1&
#8700
0&
#8710
b100 /
0%
0.
0+
b0 -
1&
#8720
0&
#8730
b1 -
1&
#8740
0&
#8750
1+
b10 -
1&
#8760
0&
#8770
0+
b0 -
1%
1.
b101 /
1&
#8780
0&
#8790
b1 -
1&
#8800
0&
#8810
1+
b10 -
1&
#8820
0&
#8830
b110 /
0%
0.
0+
b0 -
1&
#8840
0&
#8850
b1 -
1&
#8860
0&
#8870
1+
b10 -
1&
#8880
0&
#8890
0+
b0 -
1%
1.
b111 /
1&
#8900
0&
#8910
b1 -
1&
#8920
0&
#8930
1+
b10 -
1&
#8940
0&
#8950
b1000 /
0%
0.
0+
b0 -
1&
#8960
0&
#8970
b1 -
1&
#8980
0&
#8990
1+
b10 -
1&
#9000
0&
#9010
0+
b0 -
1%
1.
b1001 /
1&
#9020
0&
#9030
b1 -
1&
#9040
0&
#9050
1+
b10 -
1&
#9060
0&
#9070
b1010 /
0%
0.
0+
b0 -
1&
#9080
0&
#9090
b1 -
1&
#9100
0&
#9110
1+
b10 -
1&
#9120
0&
#9130
0+
b0 -
1%
1.
b1011 /
1&
#9140
0&
#9150
b1 -
1&
#9160
0&
#9170
1+
b10 -
1&
#9180
0&
#9190
b1100 /
0%
0.
0+
b0 -
1&
#9200
0&
#9210
b1 -
1&
#9220
0&
#9230
1+
b10 -
1&
#9240
0&
#9250
0+
b0 -
1%
1.
b1101 /
1&
#9260
0&
#9270
b1 -
1&
#9280
0&
#9290
1+
b10 -
1&
#9300
0&
#9310
b1110 /
0%
0.
0+
b0 -
1&
#9320
0&
#9330
b1 -
1&
#9340
0&
#9350
1+
b10 -
1&
#9360
0&
#9370
0+
b0 -
1%
1.
b1111 /
1&
#9380
0&
#9390
b1 -
1&
#9400
0&
#9410
1+
b10 -
1&
#9420
0&
#9430
b10000 /
0%
0.
0+
b0 -
1&
#9440
0&
#9450
b1 -
1&
#9460
0&
#9470
1+
b10 -
1&
#9480
0&
#9490
0+
b0 -
1%
1.
b10001 /
1&
#9500
0&
#9510
b1 -
1&
#9520
0&
#9530
1+
b10 -
1&
#9540
0&
#9550
b10010 /
0%
0.
0+
b0 -
1&
#9560
0&
#9570
b1 -
1&
#9580
0&
#9590
1+
b10 -
1&
#9600
0&
#9610
0+
b0 -
1%
1.
b10011 /
1&
#9620
0&
#9630
b1 -
1&
#9640
0&
#9650
1+
b10 -
1&
#9660
0&
#9670
b10100 /
0%
0.
0+
b0 -
1&
