Lab8_microphone/rtl/timer/prescaler_counter.v
module prescaler_counter (
    input wire clk,
    input wire rst_n,
    input wire enable,
    input wire [15:0] prescaler,
    output wire tick
);

    reg [15:0] count;
    reg tick_d;
    always@(posedge clk or negedge rst_n) begin
        if(!rst_n) begin
            count <= 16'h0;
            tick_d <= 0;
        end else if(enable) begin
            if(count == 16'h0) begin
                count <= prescaler == 16'h0 ? 16'h1 : prescaler;  // Prevent zero prescaler
                tick_d <= 1;
            end else begin
                count <= count - 1;
                tick_d <= 0;
            end
        end
    end

    assign tick = tick_d;

endmodule

timer/counter.v
module counter(
    input wire clk,
    input wire rst_n,
    input wire en,
    input wire start,
    input wire [15:0] prescaler,
    input wire [15:0] load,
    input wire up_down,
    input wire one_shot,
    output wire tick,
    output wire [15:0] count
);

    reg [15:0] count_d;
    reg tick_d;
    reg run;

    wire prescaler_clk;

    prescaler_counter prescaler_counter(
        .clk(clk),
        .rst_n(rst_n),
        .enable(en),
        .prescaler(prescaler),
        .tick(prescaler_clk)
    );

    always@(posedge clk or negedge rst_n) begin
        if(!rst_n) begin
            count_d <= 16'h0;
            tick_d <= 0;
        end
        else if(start) begin
            if(up_down) begin
                count_d <= 16'h0;
                run <= 1;
            end
            else begin
                count_d <= load;
                run <= 1;
            end
        end
    end

    always@(posedge prescaler_clk) begin
        if(en && run) begin
            if (one_shot) begin
                if(up_down) begin
                    if (count_d == load) begin 
                        run <= 0;
                        count_d <= 16'h0;
                        tick_d <= 1;
                    end
                    else begin
                        count_d <= count_d + 1;
                        tick_d <= 0;
                    end
                end
                else begin
                    if (count_d == 16'h0) begin
                        tick_d <= 1;
                    end
                    else begin
                        tick_d <= 0;
                        count_d = count_d - 1;
                    end
                end
            end
            else begin 
                if(up_down) begin
                    if (count_d == load) begin 
                        run <= 1;
                        count_d <= 16'h0;
                        tick_d <= 1;
                    end
                    else begin
                        count_d <= count_d + 1;
                        tick_d <= 0;
                    end
                end
                else begin
                    if (count_d == 16'h0) begin
                        run <= 1;
                        tick_d <= 1;
                        count_d <= load;
                    end
                    else begin
                        tick_d <= 0;
                        count_d = count_d - 1;
                    end
                end
            end
        end
    end

    assign tick = tick_d;
    assign count = count_d;
endmodule

timer/counter_tb.v
module counter_tb;

    reg          clk = 0;
    reg          rst_n = 0;
    reg          en;
    reg          start;
    reg          up_down;
    reg          one_shot;
    reg  [15:0]   prescaler;
    reg  [15:0]   load;
    wire         tick;

    counter duv (
        .clk(clk),
        .rst_n(rst_n),
        .en(en),
        .start(start),
        .up_down(up_down),
        .one_shot(one_shot),
        .prescaler(prescaler),
        .load(load),
        .tick(tick)
    );

    always #10 clk = !clk;

    initial begin
        #777;
        @(posedge clk);
        #1 rst_n = 1;
    end

    initial begin
        $dumpfile("counter_tb.vcd");
        $dumpvars;
    end

    initial begin
        en = 0;
        up_down = 0;
        one_shot = 1;
        prescaler = 9;
        load = 16;
        start = 0;
        wait(rst_n == 1'b1);
        @(posedge clk);
        en = 1;
        start = 1;
        @(posedge clk);
        start = 0;
        #10000;
        $finish;
    end

    initial begin
        $monitor("tick: %b",tick);
    end

endmodule

timer/counter_tb.vcd
$date
	Sun Oct 13 04:38:46 2024
$end
$version
	Icarus Verilog
$end
$timescale
	1s
$end
$scope module counter_tb $end
$var wire 1 ! tick $end
$var reg 1 " clk $end
$var reg 1 # en $end
$var reg 16 $ load [15:0] $end
$var reg 1 % one_shot $end
$var reg 16 & prescaler [15:0] $end
$var reg 1 ' rst_n $end
$var reg 1 ( start $end
$var reg 1 ) up_down $end
$scope module duv $end
$var wire 1 " clk $end
$var wire 16 * count [15:0] $end
$var wire 1 # en $end
$var wire 16 + load [15:0] $end
$var wire 1 % one_shot $end
$var wire 16 , prescaler [15:0] $end
$var wire 1 ' rst_n $end
$var wire 1 ( start $end
$var wire 1 ! tick $end
$var wire 1 ) up_down $end
$var wire 1 - prescaler_clk $end
$var reg 16 . count_d [15:0] $end
$var reg 1 / run $end
$var reg 1 0 tick_d $end
$scope module prescaler_counter $end
$var wire 1 " clk $end
$var wire 1 # enable $end
$var wire 16 1 prescaler [15:0] $end
$var wire 1 ' rst_n $end
$var wire 1 - tick $end
$var reg 16 2 count [15:0] $end
$var reg 1 3 tick_d $end
$upscope $end
$upscope $end
$upscope $end
$enddefinitions $end
#0
$dumpvars
03
b0 2
b1001 1
00
x/
b0 .
0-
b1001 ,
b10000 +
b0 *
0)
0(
0'
b1001 &
1%
b10000 $
0#
0"
0!
$end
#10
1"
#20
0"
#30
1"
#40
0"
#50
1"
#60
0"
#70
1"
#80
0"
#90
1"
#100
0"
#110
1"
#120
0"
#130
1"
#140
0"
#150
1"
#160
0"
#170
1"
#180
0"
#190
1"
#200
0"
#210
1"
#220
0"
#230
1"
#240
0"
#250
1"
#260
0"
#270
1"
#280
0"
#290
1"
#300
0"
#310
1"
#320
0"
#330
1"
#340
0"
#350
1"
#360
0"
#370
1"
#380
0"
#390
1"
#400
0"
#410
1"
#420
0"
#430
1"
#440
0"
#450
1"
#460
0"
#470
1"
#480
0"
#490
1"
#500
0"
#510
1"
#520
0"
#530
1"
#540
0"
#550
1"
#560
0"
#570
1"
#580
0"
#590
1"
#600
0"
#610
1"
#620
0"
#630
1"
#640
0"
#650
1"
#660
0"
#670
1"
#680
0"
#690
1"
#700
0"
#710
1"
#720
0"
#730
1"
#740
0"
#750
1"
#760
0"
#770
1"
#780
0"
#790
1"
#791
1'
#800
0"
#810
1/
b1111 *
b1111 .
1-
13
b1001 2
1(
1#
1"
#820
0"
#830
0-
03
b1000 2
0(
1"
#840
0"
#850
b111 2
1"
#860
0"
#870
b110 2
1"
#880
0"
#890
b101 2
1"
#900
0"
#910
b100 2
1"
#920
0"
#930
b11 2
1"
#940
0"
#950
b10 2
1"
#960
0"
#970
b1 2
1"
#980
0"
#990
b0 2
1"
#1000
0"
#1010
b1110 *
b1110 .
1-
13
b1001 2
1"
#1020
0"
#1030
0-
03
b1000 2
1"
#1040
0"
#1050
b111 2
1"
#1060
0"
#1070
b110 2
1"
#1080
0"
#1090
b101 2
1"
#1100
0"
#1110
b100 2
1"
#1120
0"
#1130
b11 2
1"
#1140
0"
#1150
b10 2
1"
#1160
0"
#1170
b1 2
1"
#1180
0"
#1190
b0 2
1"
#1200
0"
#1210
b1101 *
b1101 .
1-
13
b1001 2
1"
#1220
0"
#1230
0-
03
b1000 2
1"
#1240
0"
#1250
b111 2
1"
#1260
0"
#1270
b110 2
1"
#1280
0"
#1290
b101 2
1"
#1300
0"
#1310
b100 2
1"
#1320
0"
#1330
b11 2
1"
#1340
0"
#1350
b10 2
1"
#1360
0"
#1370
b1 2
1"
#1380
0"
#1390
b0 2
1"
#1400
0"
#1410
b1100 *
b1100 .
1-
13
b1001 2
1"
#1420
0"
#1430
0-
03
b1000 2
1"
#1440
0"
#1450
b111 2
1"
#1460
0"
#1470
b110 2
1"
#1480
0"
#1490
b101 2
1"
#1500
0"
#1510
b100 2
1"
#1520
0"
#1530
b11 2
1"
#1540
0"
#1550
b10 2
1"
#1560
0"
#1570
b1 2
1"
#1580
0"
#1590
b0 2
1"
#1600
0"
#1610
b1011 *
b1011 .
1-
13
b1001 2
1"
#1620
0"
#1630
0-
03
b1000 2
1"
#1640
0"
#1650
b111 2
1"
#1660
0"
#1670
b110 2
1"
#1680
0"
#1690
b101 2
1"
#1700
0"
#1710
b100 2
1"
#1720
0"
#1730
b11 2
1"
#1740
0"
#1750
b10 2
1"
#1760
0"
#1770
b1 2
1"
#1780
0"
#1790
b0 2
1"
#1800
0"
#1810
b1010 *
b1010 .
1-
13
b1001 2
1"
#1820
0"
#1830
0-
03
b1000 2
1"
#1840
0"
#1850
b111 2
1"
#1860
0"
#1870
b110 2
1"
#1880
0"
#1890
b101 2
1"
#1900
0"
#1910
b100 2
1"
#1920
0"
#1930
b11 2
1"
#1940
0"
#1950
b10 2
1"
#1960
0"
#1970
b1 2
1"
#1980
0"
#1990
b0 2
1"
#2000
0"
#2010
b1001 *
b1001 .
1-
13
b1001 2
1"
#2020
0"
#2030
0-
03
b1000 2
1"
#2040
0"
#2050
b111 2
1"
#2060
0"
#2070
b110 2
1"
#2080
0"
#2090
b101 2
1"
#2100
0"
#2110
b100 2
1"
#2120
0"
#2130
b11 2
1"
#2140
0"
#2150
b10 2
1"
#2160
0"
#2170
b1 2
1"
#2180
0"
#2190
b0 2
1"
#2200
0"
#2210
b1000 *
b1000 .
1-
13
b1001 2
1"
#2220
0"
#2230
0-
03
b1000 2
1"
#2240
0"
#2250
b111 2
1"
#2260
0"
#2270
b110 2
1"
#2280
0"
#2290
b101 2
1"
#2300
0"
#2310
b100 2
1"
#2320
0"
#2330
b11 2
1"
#2340
0"
#2350
b10 2
1"
#2360
0"
#2370
b1 2
1"
#2380
0"
#2390
b0 2
1"
#2400
0"
#2410
b111 *
b111 .
1-
13
b1001 2
1"
#2420
0"
#2430
0-
03
b1000 2
1"
#2440
0"
#2450
b111 2
1"
#2460
0"
#2470
b110 2
1"
#2480
0"
#2490
b101 2
1"
#2500
0"
#2510
b100 2
1"
#2520
0"
#2530
b11 2
1"
#2540
0"
#2550
b10 2
1"
#2560
0"
#2570
b1 2
1"
#2580
0"
#2590
b0 2
1"
#2600
0"
#2610
b110 *
b110 .
1-
13
b1001 2
1"
#2620
0"
#2630
0-
03
b1000 2
1"
#2640
0"
#2650
b111 2
1"
#2660
0"
#2670
b110 2
1"
#2680
0"
#2690
b101 2
1"
#2700
0"
#2710
b100 2
1"
#2720
0"
#2730
b11 2
1"
#2740
0"
#2750
b10 2
1"
#2760
0"
#2770
b1 2
1"
#2780
0"
#2790
b0 2
1"
#2800
0"
#2810
b101 *
b101 .
1-
13
b1001 2
1"
#2820
0"
#2830
0-
03
b1000 2
1"
#2840
0"
#2850
b111 2
1"
#2860
0"
#2870
b110 2
1"
#2880
0"
#2890
b101 2
1"
#2900
0"
#2910
b100 2
1"
#2920
0"
#2930
b11 2
1"
#2940
0"
#2950
b10 2
1"
#2960
0"
#2970
b1 2
1"
#2980
0"
#2990
b0 2
1"
#3000
0"
#3010
b100 *
b100 .
1-
13
b1001 2
1"
#3020
0"
#3030
0-
03
b1000 2
1"
#3040
0"
#3050
b111 2
1"
#3060
0"
#3070
b110 2
1"
#3080
0"
#3090
b101 2
1"
#3100
0"
#3110
b100 2
1"
#3120
0"
#3130
b11 2
1"
#3140
0"
#3150
b10 2
1"
#3160
0"
#3170
b1 2
1"
#3180
0"
#3190
b0 2
1"
#3200
0"
#3210
b11 *
b11 .
1-
13
b1001 2
1"
#3220
0"
#3230
0-
03
b1000 2
1"
#3240
0"
#3250
b111 2
1"
#3260
0"
#3270
b110 2
1"
#3280
0"
#3290
b101 2
1"
#3300
0"
#3310
b100 2
1"
#3320
0"
#3330
b11 2
1"
#3340
0"
#3350
b10 2
1"
#3360
0"
#3370
b1 2
1"
#3380
0"
#3390
b0 2
1"
#3400
0"
#3410
b10 *
b10 .
1-
13
b1001 2
1"
#3420
0"
#3430
0-
03
b1000 2
1"
#3440
0"
#3450
b111 2
1"
#3460
0"
#3470
b110 2
1"
#3480
0"
#3490
b101 2
1"
#3500
0"
#3510
b100 2
1"
#3520
0"
#3530
b11 2
1"
#3540
0"
#3550
b10 2
1"
#3560
0"
#3570
b1 2
1"
#3580
0"
#3590
b0 2
1"
#3600
0"
#3610
b1 *
b1 .
1-
13
b1001 2
1"
#3620
0"
#3630
0-
03
b1000 2
1"
#3640
0"
#3650
b111 2
1"
#3660
0"
#3670
b110 2
1"
#3680
0"
#3690
b101 2
1"
#3700
0"
#3710
b100 2
1"
#3720
0"
#3730
b11 2
1"
#3740
0"
#3750
b10 2
1"
#3760
0"
#3770
b1 2
1"
#3780
0"
#3790
b0 2
1"
#3800
0"
#3810
b0 *
b0 .
1-
13
b1001 2
1"
#3820
0"
#3830
0-
03
b1000 2
1"
#3840
0"
#3850
b111 2
1"
#3860
0"
#3870
b110 2
1"
#3880
0"
#3890
b101 2
1"
#3900
0"
#3910
b100 2
1"
#3920
0"
#3930
b11 2
1"
#3940
0"
#3950
b10 2
1"
#3960
0"
#3970
b1 2
1"
#3980
0"
#3990
b0 2
1"
#4000
0"
#4010
1!
10
1-
13
b1001 2
1"
#4020
0"
#4030
0-
03
b1000 2
1"
#4040
0"
#4050
b111 2
1"
#4060
0"
#4070
b110 2
1"
#4080
0"
#4090
b101 2
1"
#4100
0"
#4110
b100 2
1"
#4120
0"
#4130
b11 2
1"
#4140
0"
#4150
b10 2
1"
#4160
0"
#4170
b1 2
1"
#4180
0"
#4190
b0 2
1"
#4200
0"
#4210
1-
13
b1001 2
1"
#4220
0"
#4230
0-
03
b1000 2
1"
#4240
0"
#4250
b111 2
1"
#4260
0"
#4270
b110 2
1"
#4280
0"
#4290
b101 2
1"
#4300
0"
#4310
b100 2
1"
#4320
0"
#4330
b11 2
1"
#4340
0"
#4350
b10 2
1"
#4360
0"
#4370
b1 2
1"
#4380
0"
#4390
b0 2
1"
#4400
0"
#4410
1-
13
b1001 2
1"
#4420
0"
#4430
0-
03
b1000 2
1"
#4440
0"
#4450
b111 2
1"
#4460
0"
#4470
b110 2
1"
#4480
0"
#4490
b101 2
1"
#4500
0"
#4510
b100 2
1"
#4520
0"
#4530
b11 2
1"
#4540
0"
#4550
b10 2
1"
#4560
0"
#4570
b1 2
1"
#4580
0"
#4590
b0 2
1"
#4600
0"
#4610
1-
13
b1001 2
1"
#4620
0"
#4630
0-
03
b1000 2
1"
#4640
0"
#4650
b111 2
1"
#4660
0"
#4670
b110 2
1"
#4680
0"
#4690
b101 2
1"
#4700
0"
#4710
b100 2
1"
#4720
0"
#4730
b11 2
1"
#4740
0"
#4750
b10 2
1"
#4760
0"
#4770
b1 2
1"
#4780
0"
#4790
b0 2
1"
#4800
0"
#4810
1-
13
b1001 2
1"
#4820
0"
#4830
0-
03
b1000 2
1"
#4840
0"
#4850
b111 2
1"
#4860
0"
#4870
b110 2
1"
#4880
0"
#4890
b101 2
1"
#4900
0"
#4910
b100 2
1"
#4920
0"
#4930
b11 2
1"
#4940
0"
#4950
b10 2
1"
#4960
0"
#4970
b1 2
1"
#4980
0"
#4990
b0 2
1"
#5000
0"
#5010
1-
13
b1001 2
1"
#5020
0"
#5030
0-
03
b1000 2
1"
#5040
0"
#5050
b111 2
1"
#5060
0"
#5070
b110 2
1"
#5080
0"
#5090
b101 2
1"
#5100
0"
#5110
b100 2
1"
#5120
0"
#5130
b11 2
1"
#5140
0"
#5150
b10 2
1"
#5160
0"
#5170
b1 2
1"
#5180
0"
#5190
b0 2
1"
#5200
0"
#5210
1-
13
b1001 2
1"
#5220
0"
#5230
0-
03
b1000 2
1"
#5240
0"
#5250
b111 2
1"
#5260
0"
#5270
b110 2
1"
#5280
0"
#5290
b101 2
1"
#5300
0"
#5310
b100 2
1"
#5320
0"
#5330
b11 2
1"
#5340
0"
#5350
b10 2
1"
#5360
0"
#5370
b1 2
1"
#5380
0"
#5390
b0 2
1"
#5400
0"
#5410
1-
13
b1001 2
1"
#5420
0"
#5430
0-
03
b1000 2
1"
#5440
0"
#5450
b111 2
1"
#5460
0"
#5470
b110 2
1"
#5480
0"
#5490
b101 2
1"
#5500
0"
#5510
b100 2
1"
#5520
0"
#5530
b11 2
1"
#5540
0"
#5550
b10 2
1"
#5560
0"
#5570
b1 2
1"
#5580
0"
#5590
b0 2
1"
#5600
0"
#5610
1-
13
b1001 2
1"
#5620
0"
#5630
0-
03
b1000 2
1"
#5640
0"
#5650
b111 2
1"
#5660
0"
#5670
b110 2
1"
#5680
0"
#5690
b101 2
1"
#5700
0"
#5710
b100 2
1"
#5720
0"
#5730
b11 2
1"
#5740
0"
#5750
b10 2
1"
#5760
0"
#5770
b1 2
1"
#5780
0"
#5790
b0 2
1"
#5800
0"
#5810
1-
13
b1001 2
1"
#5820
0"
#5830
0-
03
b1000 2
1"
#5840
0"
#5850
b111 2
1"
#5860
0"
#5870
b110 2
1"
#5880
0"
#5890
b101 2
1"
#5900
0"
#5910
b100 2
1"
#5920
0"
#5930
b11 2
1"
#5940
0"
#5950
b10 2
1"
#5960
0"
#5970
b1 2
1"
#5980
0"
#5990
b0 2
1"
#6000
0"
#6010
1-
13
b1001 2
1"
#6020
0"
#6030
0-
03
b1000 2
1"
#6040
0"
#6050
b111 2
1"
#6060
0"
#6070
b110 2
1"
#6080
0"
#6090
b101 2
1"
#6100
0"
#6110
b100 2
1"
#6120
0"
#6130
b11 2
1"
#6140
0"
#6150
b10 2
1"
#6160
0"
#6170
b1 2
1"
#6180
0"
#6190
b0 2
1"
#6200
0"
#6210
1-
13
b1001 2
1"
#6220
0"
#6230
0-
03
b1000 2
1"
#6240
0"
#6250
b111 2
1"
#6260
0"
#6270
b110 2
1"
#6280
0"
#6290
b101 2
1"
#6300
0"
#6310
b100 2
1"
#6320
0"
#6330
b11 2
1"
#6340
0"
#6350
b10 2
1"
#6360
0"
#6370
b1 2
1"
#6380
0"
#6390
b0 2
1"
#6400
0"
#6410
1-
13
b1001 2
1"
#6420
0"
#6430
0-
03
b1000 2
1"
#6440
0"
#6450
b111 2
1"
#6460
0"
#6470
b110 2
1"
#6480
0"
#6490
b101 2
1"
#6500
0"
#6510
b100 2
1"
#6520
0"
#6530
b11 2
1"
#6540
0"
#6550
b10 2
1"
#6560
0"
#6570
b1 2
1"
#6580
0"
#6590
b0 2
1"
#6600
0"
#6610
1-
13
b1001 2
1"
#6620
0"
#6630
0-
03
b1000 2
1"
#6640
0"
#6650
b111 2
1"
#6660
0"
#6670
b110 2
1"
#6680
0"
#6690
b101 2
1"
#6700
0"
#6710
b100 2
1"
#6720
0"
#6730
b11 2
1"
#6740
0"
#6750
b10 2
1"
#6760
0"
#6770
b1 2
1"
#6780
0"
#6790
b0 2
1"
#6800
0"
#6810
1-
13
b1001 2
1"
#6820
0"
#6830
0-
03
b1000 2
1"
#6840
0"
#6850
b111 2
1"
#6860
0"
#6870
b110 2
1"
#6880
0"
#6890
b101 2
1"
#6900
0"
#6910
b100 2
1"
#6920
0"
#6930
b11 2
1"
#6940
0"
#6950
b10 2
1"
#6960
0"
#6970
b1 2
1"
#6980
0"
#6990
b0 2
1"
#7000
0"
#7010
1-
13
b1001 2
1"
#7020
0"
#7030
0-
03
b1000 2
1"
#7040
0"
#7050
b111 2
1"
#7060
0"
#7070
b110 2
1"
#7080
0"
#7090
b101 2
1"
#7100
0"
#7110
b100 2
1"
#7120
0"
#7130
b11 2
1"
#7140
0"
#7150
b10 2
1"
#7160
0"
#7170
b1 2
1"
#7180
0"
#7190
b0 2
1"
#7200
0"
#7210
1-
13
b1001 2
1"
#7220
0"
#7230
0-
03
b1000 2
1"
#7240
0"
#7250
b111 2
1"
#7260
0"
#7270
b110 2
1"
#7280
0"
#7290
b101 2
1"
#7300
0"
#7310
b100 2
1"
#7320
0"
#7330
b11 2
1"
#7340
0"
#7350
b10 2
1"
#7360
0"
#7370
b1 2
1"
#7380
0"
#7390
b0 2
1"
#7400
0"
#7410
1-
13
b1001 2
1"
#7420
0"
#7430
0-
03
b1000 2
1"
#7440
0"
#7450
b111 2
1"
#7460
0"
#7470
b110 2
1"
#7480
0"
#7490
b101 2
1"
#7500
0"
#7510
b100 2
1"
#7520
0"
#7530
b11 2
1"
#7540
0"
#7550
b10 2
1"
#7560
0"
#7570
b1 2
1"
#7580
0"
#7590
b0 2
1"
#7600
0"
#7610
1-
13
b1001 2
1"
#7620
0"
#7630
0-
03
b1000 2
1"
#7640
0"
#7650
b111 2
1"
#7660
0"
#7670
b110 2
1"
#7680
0"
#7690
b101 2
1"
#7700
0"
#7710
b100 2
1"
#7720
0"
#7730
b11 2
1"
#7740
0"
#7750
b10 2
1"
#7760
0"
#7770
b1 2
1"
#7780
0"
#7790
b0 2
1"
#7800
0"
#7810
1-
13
b1001 2
1"
#7820
0"
#7830
0-
03
b1000 2
1"
#7840
0"
#7850
b111 2
1"
#7860
0"
#7870
b110 2
1"
#7880
0"
#7890
b101 2
1"
#7900
0"
#7910
b100 2
1"
#7920
0"
#7930
b11 2
1"
#7940
0"
#7950
b10 2
1"
#7960
0"
#7970
b1 2
1"
#7980
0"
#7990
b0 2
1"
#8000
0"
#8010
1-
13
b1001 2
1"
#8020
0"
#8030
0-
03
b1000 2
1"
#8040
0"
#8050
b111 2
1"
#8060
0"
#8070
b110 2
1"
#8080
0"
#8090
b101 2
1"
#8100
0"
#8110
b100 2
1"
#8120
0"
#8130
b11 2
1"
#8140
0"
#8150
b10 2
1"
#8160
0"
#8170
b1 2
1"
#8180
0"
#8190
b0 2
1"
#8200
0"
#8210
1-
13
b1001 2
1"
#8220
0"
#8230
0-
03
b1000 2
1"
#8240
0"
#8250
b111 2
1"
#8260
0"
#8270
b110 2
1"
#8280
0"
#8290
b101 2
1"
#8300
0"
#8310
b100 2
1"
#8320
0"
#8330
b11 2
1"
#8340
0"
#8350
b10 2
1"
#8360
0"
#8370
b1 2
1"
#8380
0"
#8390
b0 2
1"
#8400
0"
#8410
1-
13
b1001 2
1"
#8420
0"
#8430
0-
03
b1000 2
1"
#8440
0"
#8450
b111 2
1"
#8460
0"
#8470
b110 2
1"
#8480
0"
#8490
b101 2
1"
#8500
0"
#8510
b100 2
1"
#8520
0"
#8530
b11 2
1"
#8540
0"
#8550
b10 2
1"
#8560
0"
#8570
b1 2
1"
#8580
0"
#8590
b0 2
1"
#8600
0"
#8610
1-
13
b1001 2
1"
#8620
0"
#8630
0-
03
b1000 2
1"
#8640
0"
#8650
b111 2
1"
#8660
0"
#8670
b110 2
1"
#8680
0"
#8690
b101 2
1"
#8700
0"
#8710
b100 2
1"
#8720
0"
#8730
b11 2
1"
#8740
0"
#8750
b10 2
1"
#8760
0"
#8770
b1 2
1"
#8780
0"
#8790
b0 2
1"
#8800
0"
#8810
1-
13
b1001 2
1"
#8820
0"
#8830
0-
03
b1000 2
1"
#8840
0"
#8850
b111 2
1"
#8860
0"
#8870
b110 2
1"
#8880
0"
#8890
b101 2
1"
#8900
0"
#8910
b100 2
1"
#8920
0"
#8930
b11 2
1"
#8940
0"
#8950
b10 2
1"
#8960
0"
#8970
b1 2
1"
#8980
0"
#8990
b0 2
1"
#9000
0"
#9010
1-
13
b1001 2
1"
#9020
0"
#9030
0-
03
b1000 2
1"
#9040
0"
#9050
b111 2
1"
#9060
0"
#9070
b110 2
1"
#9080
0"
#9090
b101 2
1"
#9100
0"
#9110
b100 2
1"
#9120
0"
#9130
b11 2
1"
#9140
0"
#9150
b10 2
1"
#9160
0"
#9170
b1 2
1"
#9180
0"
#9190
b0 2
1"
#9200
0"
#9210
1-
13
b1001 2
1"
#9220
0"
#9230
0-
03
b1000 2
1"
#9240
0"
#9250
b111 2
1"
#9260
0"
#9270
b110 2
1"
#9280
0"
#9290
b101 2
1"
#9300
0"
#9310
b100 2
1"
#9320
0"
#9330
b11 2
1"
#9340
0"
#9350
b10 2
1"
#9360
0"
#9370
b1 2
1"
#9380
0"
#9390
b0 2
1"
#9400
0"
#9410
1-
13
b1001 2
1"
#9420
0"
#9430
0-
03
b1000 2
1"
#9440
0"
#9450
b111 2
1"
#9460
0"
#9470
b110 2
1"
#9480
0"
#9490
b101 2
1"
#9500
0"
#9510
b100 2
1"
#9520
0"
#9530
b11 2
1"
#9540
0"
#9550
b10 2
1"
#9560
0"
#9570
b1 2
1"
#9580
0"
#9590
b0 2
1"
#9600
0"
#9610
1-
13
b1001 2
1"
#9620
0"
#9630
0-
03
b1000 2
1"
#9640
0"
#9650
b111 2
1"
#9660
0"
#9670
b110 2
1"
#9680
0"
#9690
b101 2
1"
#9700
0"
#9710
b100 2
1"
#9720
0"
#9730
b11 2
1"
#9740
0"
#9750
b10 2
1"
#9760
0"
#9770
b1 2
1"
#9780
0"
#9790
b0 2
1"
#9800
0"
#9810
1-
13
b1001 2
1"
#9820
0"
#9830
0-
03
b1000 2
1"
#9840
0"
#9850
b111 2
1"
#9860
0"
#9870
b110 2
1"
#9880
0"
#9890
b101 2
1"
#9900
0"
#9910
b100 2
1"
#9920
0"
#9930
b11 2
1"
#9940
0"
#9950
b10 2
1"
#9960
0"
#9970
b1 2
1"
#9980
0"
#9990
b0 2
1"
#10000
0"
#10010
1-
13
b1001 2
1"
#10020
0"
#10030
0-
03
b1000 2
1"
#10040
0"
#10050
b111 2
1"
#10060
0"
#10070
b110 2
1"
#10080
0"
#10090
b101 2
1"
#10100
0"
#10110
b100 2
1"
#10120
0"
#10130
b11 2
1"
#10140
0"
#10150
b10 2
1"
#10160
0"
#10170
b1 2
1"
#10180
0"
#10190
b0 2
1"
#10200
0"
#10210
1-
13
b1001 2
1"
#10220
0"
#10230
0-
03
b1000 2
1"
#10240
0"
#10250
b111 2
1"
#10260
0"
#10270
b110 2
1"
#10280
0"
#10290
b101 2
1"
#10300
0"
#10310
b100 2
1"
#10320
0"
#10330
b11 2
1"
#10340
0"
#10350
b10 2
1"
#10360
0"
#10370
b1 2
1"
#10380
0"
#10390
b0 2
1"
#10400
0"
#10410
1-
13
b1001 2
1"
#10420
0"
#10430
0-
03
b1000 2
1"
#10440
0"
#10450
b111 2
1"
#10460
0"
#10470
b110 2
1"
#10480
0"
#10490
b101 2
1"
#10500
0"
#10510
b100 2
1"
#10520
0"
#10530
b11 2
1"
#10540
0"
#10550
b10 2
1"
#10560
0"
#10570
b1 2
1"
#10580
0"
#10590
b0 2
1"
#10600
0"
#10610
1-
13
b1001 2
1"
#10620
0"
#10630
0-
03
b1000 2
1"
#10640
0"
#10650
b111 2
1"
#10660
0"
#10670
b110 2
1"
#10680
0"
#10690
b101 2
1"
#10700
0"
#10710
b100 2
1"
#10720
0"
#10730
b11 2
1"
#10740
0"
#10750
b10 2
1"
#10760
0"
#10770
b1 2
1"
#10780
0"
#10790
b0 2
1"
#10800
0"
#10810
1-
13
b1001 2
1"
#10820
0"
#10830
0-
03
b1000 2
1"
